Workbook

Sheet Главная
B2: КОНТРОЛЬ РАБОЧИХ ЗАДАЧ
B3: Сегодня: | C3: =TODAY() -> 46301 | E3: Данные вводите на листе «Задачи» — всё остальное обновляется само.
B5: СВОДКА | E5: ФИЛЬТР СПИСКОВ НИЖЕ
B6: Всего активных задач | C6: =COUNTIF(Задачи!$J$2:$J$501,"Срочные")+COUNTIF(Задачи!$J$2:$J$501,"Текущие")+COUNTIF(Задачи!$J$2:$J$501,"Плановые") -> 29 | E6: Категория | F6: Все
B7: Срочных (приоритет «Срочно») | C7: =COUNTIFS(Задачи!$C$2:$C$501,"Срочно",Задачи!$J$2:$J$501,"Срочные") -> 1 | E7: Приоритет | F7: Все
B8: Просрочено | C8: =SUMPRODUCT((Задачи!$J$2:$J$501<>"")*(Задачи!$J$2:$J$501<>"Выполнено")*(Задачи!$F$2:$F$501<>"")*(Задачи!$F$2:$F$501<TODAY())) -> 0
B9: Срок в ближайшие 3 дня | C9: =SUMPRODUCT((Задачи!$J$2:$J$501<>"")*(Задачи!$J$2:$J$501<>"Выполнено")*(Задачи!$F$2:$F$501<>"")*(Задачи!$F$2:$F$501>=TODAY())*(Задачи!$F$2:$F$501<=TODAY()+3)) -> 8 | E9: Как распределяются задачи:
B10: В работе | C10: =COUNTIF(Задачи!$D$2:$D$501,"В работе") -> 7 | E10: • Срочные — приоритет «Срочно», срок сегодня или просрочен
B11: Ожидают | C11: =COUNTIF(Задачи!$D$2:$D$501,"Ожидает") -> 1 | E11: • Плановые — «Отложено», приоритет «Низкий» или срок далее чем через 7 дней
B12: Выполнено | C12: =COUNTIF(Задачи!$J$2:$J$501,"Выполнено") -> 8 | E12: • Текущие — всё остальное; «Выполнено» уходит в отдельный лист
B14: ="СРОЧНЫЕ И ПРОСРОЧЕННЫЕ · "&COUNT(Задачи!$M$2:$M$501)&IF(COUNT(Задачи!$M$2:$M$501)>8," (показаны первые 8, остальные — на листе «Задачи»)","") -> СРОЧНЫЕ И ПРОСРОЧЕННЫЕ · 4
B15: Задача | C15: Категория | D15: Приоритет | E15: Статус | F15: Срок | G15: Осталось | H15: Комментарий / результат | I15: Стр.
B16: =IF($I16="","",INDEX(Задачи!$A$1:$A$501,$I16)&"") -> Закончить регламент сотрудников | C16: =IF($I16="","",INDEX(Задачи!$B$1:$B$501,$I16)&"") -> Управление | D16: =IF($I16="","",INDEX(Задачи!$C$1:$C$501,$I16)&"") -> Срочно | E16: =IF($I16="","",IF(INDEX(Задачи!$D$1:$D$501,$I16)="","Не начато",INDEX(Задачи!$D$1:$D$501,$I16))) -> В работе | F16: =IF($I16="","",IF(INDEX(Задачи!$F$1:$F$501,$I16)="","",INDEX(Задачи!$F$1:$F$501,$I16))) -> 46301 | G16: =IF($I16="","",INDEX(Задачи!$K$1:$K$501,$I16)&"") -> Сегодня | H16: =IF($I16="","",INDEX(Задачи!$I$1:$I$501,$I16)&"") -> в трудовом договоре указать налогии | I16: =IFERROR(MOD(SMALL(Задачи!$M$2:$M$501,ROWS(I$16:I16)),1000),"") -> 11
B17: =IF($I17="","",INDEX(Задачи!$A$1:$A$501,$I17)&"") -> Пожарная безопасность | C17: =IF($I17="","",INDEX(Задачи!$B$1:$B$501,$I17)&"") -> Оптовка | D17: =IF($I17="","",INDEX(Задачи!$C$1:$C$501,$I17)&"") -> Высокий | E17: =IF($I17="","",IF(INDEX(Задачи!$D$1:$D$501,$I17)="","Не начато",INDEX(Задачи!$D$1:$D$501,$I17))) -> В работе | F17: =IF($I17="","",IF(INDEX(Задачи!$F$1:$F$501,$I17)="","",INDEX(Задачи!$F$1:$F$501,$I17))) -> 46301 | G17: =IF($I17="","",INDEX(Задачи!$K$1:$K$501,$I17)&"") -> Сегодня | H17: =IF($I17="","",INDEX(Задачи!$I$1:$I$501,$I17)&"") -> вопрос делегирован Улжану | I17: =IFERROR(MOD(SMALL(Задачи!$M$2:$M$501,ROWS(I$16:I17)),1000),"") -> 16
B18: =IF($I18="","",INDEX(Задачи!$A$1:$A$501,$I18)&"") -> Съездить в общежитие и снять фото/видео и зикр выставять обьяв | C18: =IF($I18="","",INDEX(Задачи!$B$1:$B$501,$I18)&"") -> Недвижимость | D18: =IF($I18="","",INDEX(Задачи!$C$1:$C$501,$I18)&"") -> Средний | E18: =IF($I18="","",IF(INDEX(Задачи!$D$1:$D$501,$I18)="","Не начато",INDEX(Задачи!$D$1:$D$501,$I18))) -> Не начато | F18: =IF($I18="","",IF(INDEX(Задачи!$F$1:$F$501,$I18)="","",INDEX(Задачи!$F$1:$F$501,$I18))) -> 46301 | G18: =IF($I18="","",INDEX(Задачи!$K$1:$K$501,$I18)&"") -> Сегодня | H18: =IF($I18="","",INDEX(Задачи!$I$1:$I$501,$I18)&"") | I18: =IFERROR(MOD(SMALL(Задачи!$M$2:$M$501,ROWS(I$16:I18)),1000),"") -> 13
B19: =IF($I19="","",INDEX(Задачи!$A$1:$A$501,$I19)&"") -> Даулет мырза набрать, напомнить,Улжана передать на поле | C19: =IF($I19="","",INDEX(Задачи!$B$1:$B$501,$I19)&"") -> Оптовка | D19: =IF($I19="","",INDEX(Задачи!$C$1:$C$501,$I19)&"") -> Средний | E19: =IF($I19="","",IF(INDEX(Задачи!$D$1:$D$501,$I19)="","Не начато",INDEX(Задачи!$D$1:$D$501,$I19))) -> Ожидает | F19: =IF($I19="","",IF(INDEX(Задачи!$F$1:$F$501,$I19)="","",INDEX(Задачи!$F$1:$F$501,$I19))) -> 46301 | G19: =IF($I19="","",INDEX(Задачи!$K$1:$K$501,$I19)&"") -> Сегодня | H19: =IF($I19="","",INDEX(Задачи!$I$1:$I$501,$I19)&"") | I19: =IFERROR(MOD(SMALL(Задачи!$M$2:$M$501,ROWS(I$16:I19)),1000),"") -> 19
B20: =IF($I20="","",INDEX(Задачи!$A$1:$A$501,$I20)&"") | C20: =IF($I20="","",INDEX(Задачи!$B$1:$B$501,$I20)&"") | D20: =IF($I20="","",INDEX(Задачи!$C$1:$C$501,$I20)&"") | E20: =IF($I20="","",IF(INDEX(Задачи!$D$1:$D$501,$I20)="","Не начато",INDEX(Задачи!$D$1:$D$501,$I20))) | F20: =IF($I20="","",IF(INDEX(Задачи!$F$1:$F$501,$I20)="","",INDEX(Задачи!$F$1:$F$501,$I20))) | G20: =IF($I20="","",INDEX(Задачи!$K$1:$K$501,$I20)&"") | H20: =IF($I20="","",INDEX(Задачи!$I$1:$I$501,$I20)&"") | I20: =IFERROR(MOD(SMALL(Задачи!$M$2:$M$501,ROWS(I$16:I20)),1000),"")
B21: =IF($I21="","",INDEX(Задачи!$A$1:$A$501,$I21)&"") | C21: =IF($I21="","",INDEX(Задачи!$B$1:$B$501,$I21)&"") | D21: =IF($I21="","",INDEX(Задачи!$C$1:$C$501,$I21)&"") | E21: =IF($I21="","",IF(INDEX(Задачи!$D$1:$D$501,$I21)="","Не начато",INDEX(Задачи!$D$1:$D$501,$I21))) | F21: =IF($I21="","",IF(INDEX(Задачи!$F$1:$F$501,$I21)="","",INDEX(Задачи!$F$1:$F$501,$I21))) | G21: =IF($I21="","",INDEX(Задачи!$K$1:$K$501,$I21)&"") | H21: =IF($I21="","",INDEX(Задачи!$I$1:$I$501,$I21)&"") | I21: =IFERROR(MOD(SMALL(Задачи!$M$2:$M$501,ROWS(I$16:I21)),1000),"")
B22: =IF($I22="","",INDEX(Задачи!$A$1:$A$501,$I22)&"") | C22: =IF($I22="","",INDEX(Задачи!$B$1:$B$501,$I22)&"") | D22: =IF($I22="","",INDEX(Задачи!$C$1:$C$501,$I22)&"") | E22: =IF($I22="","",IF(INDEX(Задачи!$D$1:$D$501,$I22)="","Не начато",INDEX(Задачи!$D$1:$D$501,$I22))) | F22: =IF($I22="","",IF(INDEX(Задачи!$F$1:$F$501,$I22)="","",INDEX(Задачи!$F$1:$F$501,$I22))) | G22: =IF($I22="","",INDEX(Задачи!$K$1:$K$501,$I22)&"") | H22: =IF($I22="","",INDEX(Задачи!$I$1:$I$501,$I22)&"") | I22: =IFERROR(MOD(SMALL(Задачи!$M$2:$M$501,ROWS(I$16:I22)),1000),"")
B23: =IF($I23="","",INDEX(Задачи!$A$1:$A$501,$I23)&"") | C23: =IF($I23="","",INDEX(Задачи!$B$1:$B$501,$I23)&"") | D23: =IF($I23="","",INDEX(Задачи!$C$1:$C$501,$I23)&"") | E23: =IF($I23="","",IF(INDEX(Задачи!$D$1:$D$501,$I23)="","Не начато",INDEX(Задачи!$D$1:$D$501,$I23))) | F23: =IF($I23="","",IF(INDEX(Задачи!$F$1:$F$501,$I23)="","",INDEX(Задачи!$F$1:$F$501,$I23))) | G23: =IF($I23="","",INDEX(Задачи!$K$1:$K$501,$I23)&"") | H23: =IF($I23="","",INDEX(Задачи!$I$1:$I$501,$I23)&"") | I23: =IFERROR(MOD(SMALL(Задачи!$M$2:$M$501,ROWS(I$16:I23)),1000),"")
B25: ="ТЕКУЩИЕ · "&COUNT(Задачи!$N$2:$N$501)&IF(COUNT(Задачи!$N$2:$N$501)>28," (показаны первые 28, остальные — на листе «Задачи»)","") -> ТЕКУЩИЕ · 22
B26: Задача | C26: Категория | D26: Приоритет | E26: Статус | F26: Срок | G26: Осталось | H26: Комментарий / результат | I26: Стр.
B27: =IF($I27="","",INDEX(Задачи!$A$1:$A$501,$I27)&"") -> Договор о неразглашений конф информации, подписать всех сотрудников | C27: =IF($I27="","",INDEX(Задачи!$B$1:$B$501,$I27)&"") -> Управление | D27: =IF($I27="","",INDEX(Задачи!$C$1:$C$501,$I27)&"") -> Высокий | E27: =IF($I27="","",IF(INDEX(Задачи!$D$1:$D$501,$I27)="","Не начато",INDEX(Задачи!$D$1:$D$501,$I27))) -> В работе | F27: =IF($I27="","",IF(INDEX(Задачи!$F$1:$F$501,$I27)="","",INDEX(Задачи!$F$1:$F$501,$I27))) -> 46302 | G27: =IF($I27="","",INDEX(Задачи!$K$1:$K$501,$I27)&"") -> Завтра | H27: =IF($I27="","",INDEX(Задачи!$I$1:$I$501,$I27)&"") -> отделам отправила весь регламент жду пописи | I27: =IFERROR(MOD(SMALL(Задачи!$N$2:$N$501,ROWS(I$27:I27)),1000),"") -> 24
B28: =IF($I28="","",INDEX(Задачи!$A$1:$A$501,$I28)&"") -> Зарегистровать компанию в портал Алеумет | C28: =IF($I28="","",INDEX(Задачи!$B$1:$B$501,$I28)&"") -> Подгузники / маркетинг | D28: =IF($I28="","",INDEX(Задачи!$C$1:$C$501,$I28)&"") -> Высокий | E28: =IF($I28="","",IF(INDEX(Задачи!$D$1:$D$501,$I28)="","Не начато",INDEX(Задачи!$D$1:$D$501,$I28))) -> Не начато | F28: =IF($I28="","",IF(INDEX(Задачи!$F$1:$F$501,$I28)="","",INDEX(Задачи!$F$1:$F$501,$I28))) -> 46304 | G28: =IF($I28="","",INDEX(Задачи!$K$1:$K$501,$I28)&"") -> Через 3 дн. | H28: =IF($I28="","",INDEX(Задачи!$I$1:$I$501,$I28)&"") -> эцп,декларация о соответствии подтв соответсвия, регистрационное удостоверение, док сертификат, регистрационные дркументы, сведение о товаре цена ,все данные компании ТОО,запросить у Гульжайны, | I28: =IFERROR(MOD(SMALL(Задачи!$N$2:$N$501,ROWS(I$27:I28)),1000),"") -> 20
B29: =IF($I29="","",INDEX(Задачи!$A$1:$A$501,$I29)&"") -> Контролировать таргет по промбазе: заявки, стоимость лида, качество обращений | C29: =IF($I29="","",INDEX(Задачи!$B$1:$B$501,$I29)&"") -> Промбаза / маркетинг | D29: =IF($I29="","",INDEX(Задачи!$C$1:$C$501,$I29)&"") -> Высокий | E29: =IF($I29="","",IF(INDEX(Задачи!$D$1:$D$501,$I29)="","Не начато",INDEX(Задачи!$D$1:$D$501,$I29))) -> В работе | F29: =IF($I29="","",IF(INDEX(Задачи!$F$1:$F$501,$I29)="","",INDEX(Задачи!$F$1:$F$501,$I29))) | G29: =IF($I29="","",INDEX(Задачи!$K$1:$K$501,$I29)&"") -> ↻ Ежедневно | H29: =IF($I29="","",INDEX(Задачи!$I$1:$I$501,$I29)&"") | I29: =IFERROR(MOD(SMALL(Задачи!$N$2:$N$501,ROWS(I$27:I29)),1000),"") -> 4
B30: =IF($I30="","",INDEX(Задачи!$A$1:$A$501,$I30)&"") -> Поиск сотрудника — приёмщик | C30: =IF($I30="","",INDEX(Задачи!$B$1:$B$501,$I30)&"") -> Найм | D30: =IF($I30="","",INDEX(Задачи!$C$1:$C$501,$I30)&"") -> Высокий | E30: =IF($I30="","",IF(INDEX(Задачи!$D$1:$D$501,$I30)="","Не начато",INDEX(Задачи!$D$1:$D$501,$I30))) -> В работе | F30: =IF($I30="","",IF(INDEX(Задачи!$F$1:$F$501,$I30)="","",INDEX(Задачи!$F$1:$F$501,$I30))) | G30: =IF($I30="","",INDEX(Задачи!$K$1:$K$501,$I30)&"") -> ↻ Ежедневно | H30: =IF($I30="","",INDEX(Задачи!$I$1:$I$501,$I30)&"") -> подала объявление в НН, Каспи Периодичность: ежедневно до закрытия | I30: =IFERROR(MOD(SMALL(Задачи!$N$2:$N$501,ROWS(I$27:I30)),1000),"") -> 5
B31: =IF($I31="","",INDEX(Задачи!$A$1:$A$501,$I31)&"") -> Поиск SMM-специалиста | C31: =IF($I31="","",INDEX(Задачи!$B$1:$B$501,$I31)&"") -> Найм | D31: =IF($I31="","",INDEX(Задачи!$C$1:$C$501,$I31)&"") -> Высокий | E31: =IF($I31="","",IF(INDEX(Задачи!$D$1:$D$501,$I31)="","Не начато",INDEX(Задачи!$D$1:$D$501,$I31))) -> В работе | F31: =IF($I31="","",IF(INDEX(Задачи!$F$1:$F$501,$I31)="","",INDEX(Задачи!$F$1:$F$501,$I31))) | G31: =IF($I31="","",INDEX(Задачи!$K$1:$K$501,$I31)&"") -> ↻ Ежедневно | H31: =IF($I31="","",INDEX(Задачи!$I$1:$I$501,$I31)&"") -> Периодичность: ежедневно до закрытия | I31: =IFERROR(MOD(SMALL(Задачи!$N$2:$N$501,ROWS(I$27:I31)),1000),"") -> 6
B32: =IF($I32="","",INDEX(Задачи!$A$1:$A$501,$I32)&"") -> Поиск торгового менеджера | C32: =IF($I32="","",INDEX(Задачи!$B$1:$B$501,$I32)&"") -> Найм | D32: =IF($I32="","",INDEX(Задачи!$C$1:$C$501,$I32)&"") -> Высокий | E32: =IF($I32="","",IF(INDEX(Задачи!$D$1:$D$501,$I32)="","Не начато",INDEX(Задачи!$D$1:$D$501,$I32))) -> Не начато | F32: =IF($I32="","",IF(INDEX(Задачи!$F$1:$F$501,$I32)="","",INDEX(Задачи!$F$1:$F$501,$I32))) | G32: =IF($I32="","",INDEX(Задачи!$K$1:$K$501,$I32)&"") -> ↻ Ежедневно | H32: =IF($I32="","",INDEX(Задачи!$I$1:$I$501,$I32)&"") -> Шеф: 200 оклад, план на 10 млн -1% от продаж, график 6/1 , 100 тыс дорожный + обед | I32: =IFERROR(MOD(SMALL(Задачи!$N$2:$N$501,ROWS(I$27:I32)),1000),"") -> 7
B33: =IF($I33="","",INDEX(Задачи!$A$1:$A$501,$I33)&"") -> Поиск регионального менеджера | C33: =IF($I33="","",INDEX(Задачи!$B$1:$B$501,$I33)&"") -> Найм | D33: =IF($I33="","",INDEX(Задачи!$C$1:$C$501,$I33)&"") -> Высокий | E33: =IF($I33="","",IF(INDEX(Задачи!$D$1:$D$501,$I33)="","Не начато",INDEX(Задачи!$D$1:$D$501,$I33))) -> Не начато | F33: =IF($I33="","",IF(INDEX(Задачи!$F$1:$F$501,$I33)="","",INDEX(Задачи!$F$1:$F$501,$I33))) | G33: =IF($I33="","",INDEX(Задачи!$K$1:$K$501,$I33)&"") -> ↻ Ежедневно | H33: =IF($I33="","",INDEX(Задачи!$I$1:$I$501,$I33)&"") -> Периодичность: ежедневно до закрытия | I33: =IFERROR(MOD(SMALL(Задачи!$N$2:$N$501,ROWS(I$27:I33)),1000),"") -> 8
B34: =IF($I34="","",INDEX(Задачи!$A$1:$A$501,$I34)&"") -> Разместить общежитие на Krisha.kz после съёмки | C34: =IF($I34="","",INDEX(Задачи!$B$1:$B$501,$I34)&"") -> Недвижимость | D34: =IF($I34="","",INDEX(Задачи!$C$1:$C$501,$I34)&"") -> Средний | E34: =IF($I34="","",IF(INDEX(Задачи!$D$1:$D$501,$I34)="","Не начато",INDEX(Задачи!$D$1:$D$501,$I34))) -> Не начато | F34: =IF($I34="","",IF(INDEX(Задачи!$F$1:$F$501,$I34)="","",INDEX(Задачи!$F$1:$F$501,$I34))) -> 46302 | G34: =IF($I34="","",INDEX(Задачи!$K$1:$K$501,$I34)&"") -> Завтра | H34: =IF($I34="","",INDEX(Задачи!$I$1:$I$501,$I34)&"") | I34: =IFERROR(MOD(SMALL(Задачи!$N$2:$N$501,ROWS(I$27:I34)),1000),"") -> 14
B35: =IF($I35="","",INDEX(Задачи!$A$1:$A$501,$I35)&"") -> Паспорт Объекта | C35: =IF($I35="","",INDEX(Задачи!$B$1:$B$501,$I35)&"") -> Оптовка | D35: =IF($I35="","",INDEX(Задачи!$C$1:$C$501,$I35)&"") -> Средний | E35: =IF($I35="","",IF(INDEX(Задачи!$D$1:$D$501,$I35)="","Не начато",INDEX(Задачи!$D$1:$D$501,$I35))) -> Не начато | F35: =IF($I35="","",IF(INDEX(Задачи!$F$1:$F$501,$I35)="","",INDEX(Задачи!$F$1:$F$501,$I35))) -> 46302 | G35: =IF($I35="","",INDEX(Задачи!$K$1:$K$501,$I35)&"") -> Завтра | H35: =IF($I35="","",INDEX(Задачи!$I$1:$I$501,$I35)&"") -> Регина Улан | I35: =IFERROR(MOD(SMALL(Задачи!$N$2:$N$501,ROWS(I$27:I35)),1000),"") -> 15
B36: =IF($I36="","",INDEX(Задачи!$A$1:$A$501,$I36)&"") -> Продать машины грузовые, обновить все машины,машину по под 0 процентов, от3 до5 лизинг | C36: =IF($I36="","",INDEX(Задачи!$B$1:$B$501,$I36)&"") -> Управление | D36: =IF($I36="","",INDEX(Задачи!$C$1:$C$501,$I36)&"") -> Средний | E36: =IF($I36="","",IF(INDEX(Задачи!$D$1:$D$501,$I36)="","Не начато",INDEX(Задачи!$D$1:$D$501,$I36))) -> В работе | F36: =IF($I36="","",IF(INDEX(Задачи!$F$1:$F$501,$I36)="","",INDEX(Задачи!$F$1:$F$501,$I36))) | G36: =IF($I36="","",INDEX(Задачи!$K$1:$K$501,$I36)&"") -> ↻ Ежедневно | H36: =IF($I36="","",INDEX(Задачи!$I$1:$I$501,$I36)&"") -> от 5 до 10 млн, 5 тонник груз подьем 6-8 тонн | I36: =IFERROR(MOD(SMALL(Задачи!$N$2:$N$501,ROWS(I$27:I36)),1000),"") -> 26
B37: =IF($I37="","",INDEX(Задачи!$A$1:$A$501,$I37)&"") -> Страхование жизни уточнить взять КП | C37: =IF($I37="","",INDEX(Задачи!$B$1:$B$501,$I37)&"") -> Управление | D37: =IF($I37="","",INDEX(Задачи!$C$1:$C$501,$I37)&"") | E37: =IF($I37="","",IF(INDEX(Задачи!$D$1:$D$501,$I37)="","Не начато",INDEX(Задачи!$D$1:$D$501,$I37))) -> Не начато | F37: =IF($I37="","",IF(INDEX(Задачи!$F$1:$F$501,$I37)="","",INDEX(Задачи!$F$1:$F$501,$I37))) | G37: =IF($I37="","",INDEX(Задачи!$K$1:$K$501,$I37)&"") | H37: =IF($I37="","",INDEX(Задачи!$I$1:$I$501,$I37)&"") | I37: =IFERROR(MOD(SMALL(Задачи!$N$2:$N$501,ROWS(I$27:I37)),1000),"") -> 18
B38: =IF($I38="","",INDEX(Задачи!$A$1:$A$501,$I38)&"") -> вторник пятница в область машины отгрузки не ездят в Основном все фуры по регионам стоят | C38: =IF($I38="","",INDEX(Задачи!$B$1:$B$501,$I38)&"") -> Оптовка | D38: =IF($I38="","",INDEX(Задачи!$C$1:$C$501,$I38)&"") | E38: =IF($I38="","",IF(INDEX(Задачи!$D$1:$D$501,$I38)="","Не начато",INDEX(Задачи!$D$1:$D$501,$I38))) -> Не начато | F38: =IF($I38="","",IF(INDEX(Задачи!$F$1:$F$501,$I38)="","",INDEX(Задачи!$F$1:$F$501,$I38))) | G38: =IF($I38="","",INDEX(Задачи!$K$1:$K$501,$I38)&"") | H38: =IF($I38="","",INDEX(Задачи!$I$1:$I$501,$I38)&"") | I38: =IFERROR(MOD(SMALL(Задачи!$N$2:$N$501,ROWS(I$27:I38)),1000),"") -> 25
... B54: =IF($I54="","",INDEX(Задачи!$A$1:$A$501,$I54)&"") | C54: =IF($I54="","",INDEX(Задачи!$B$1:$B$501,$I54)&"") | D54: =IF($I54="","",INDEX(Задачи!$C$1:$C$501,$I54)&"") | E54: =IF($I54="","",IF(INDEX(Задачи!$D$1:$D$501,$I54)="","Не начато",INDEX(Задачи!$D$1:$D$501,$I54))) | F54: =IF($I54="","",IF(INDEX(Задачи!$F$1:$F$501,$I54)="","",INDEX(Задачи!$F$1:$F$501,$I54))) | G54: =IF($I54="","",INDEX(Задачи!$K$1:$K$501,$I54)&"") | H54: =IF($I54="","",INDEX(Задачи!$I$1:$I$501,$I54)&"") | I54: =IFERROR(MOD(SMALL(Задачи!$N$2:$N$501,ROWS(I$27:I54)),1000),"")
B56: ="ПЛАНОВЫЕ · "&COUNT(Задачи!$O$2:$O$501)&IF(COUNT(Задачи!$O$2:$O$501)>12," (показаны первые 12, остальные — на листе «Задачи»)","") -> ПЛАНОВЫЕ · 3
B57: Задача | C57: Категория | D57: Приоритет | E57: Статус | F57: Срок | G57: Осталось | H57: Комментарий / результат | I57: Стр.
B58: =IF($I58="","",INDEX(Задачи!$A$1:$A$501,$I58)&"") -> Продвижение подгузников: идеи, контент, каналы продвижения, контроль,Посик UGS креаторов, блогеров | C58: =IF($I58="","",INDEX(Задачи!$B$1:$B$501,$I58)&"") -> Подгузники / маркетинг | D58: =IF($I58="","",INDEX(Задачи!$C$1:$C$501,$I58)&"") -> Высокий | E58: =IF($I58="","",IF(INDEX(Задачи!$D$1:$D$501,$I58)="","Не начато",INDEX(Задачи!$D$1:$D$501,$I58))) -> Отложено | F58: =IF($I58="","",IF(INDEX(Задачи!$F$1:$F$501,$I58)="","",INDEX(Задачи!$F$1:$F$501,$I58))) | G58: =IF($I58="","",INDEX(Задачи!$K$1:$K$501,$I58)&"") -> ↻ Ежедневно | H58: =IF($I58="","",INDEX(Задачи!$I$1:$I$501,$I58)&"") -> совместо с маркетологом будем работать | I58: =IFERROR(MOD(SMALL(Задачи!$O$2:$O$501,ROWS(I$58:I58)),1000),"") -> 10
B59: =IF($I59="","",INDEX(Задачи!$A$1:$A$501,$I59)&"") -> миграционные вопросы решить по трудоустройстве | C59: =IF($I59="","",INDEX(Задачи!$B$1:$B$501,$I59)&"") -> Управление | D59: =IF($I59="","",INDEX(Задачи!$C$1:$C$501,$I59)&"") -> Высокий | E59: =IF($I59="","",IF(INDEX(Задачи!$D$1:$D$501,$I59)="","Не начато",INDEX(Задачи!$D$1:$D$501,$I59))) -> Отложено | F59: =IF($I59="","",IF(INDEX(Задачи!$F$1:$F$501,$I59)="","",INDEX(Задачи!$F$1:$F$501,$I59))) | G59: =IF($I59="","",INDEX(Задачи!$K$1:$K$501,$I59)&"") | H59: =IF($I59="","",INDEX(Задачи!$I$1:$I$501,$I59)&"") | I59: =IFERROR(MOD(SMALL(Задачи!$O$2:$O$501,ROWS(I$58:I59)),1000),"") -> 28
B60: =IF($I60="","",INDEX(Задачи!$A$1:$A$501,$I60)&"") -> Светофор магазин, по ним ждем Ханни | C60: =IF($I60="","",INDEX(Задачи!$B$1:$B$501,$I60)&"") -> Подгузники / маркетинг | D60: =IF($I60="","",INDEX(Задачи!$C$1:$C$501,$I60)&"") -> Средний | E60: =IF($I60="","",IF(INDEX(Задачи!$D$1:$D$501,$I60)="","Не начато",INDEX(Задачи!$D$1:$D$501,$I60))) -> Отложено | F60: =IF($I60="","",IF(INDEX(Задачи!$F$1:$F$501,$I60)="","",INDEX(Задачи!$F$1:$F$501,$I60))) | G60: =IF($I60="","",INDEX(Задачи!$K$1:$K$501,$I60)&"") | H60: =IF($I60="","",INDEX(Задачи!$I$1:$I$501,$I60)&"") | I60: =IFERROR(MOD(SMALL(Задачи!$O$2:$O$501,ROWS(I$58:I60)),1000),"") -> 27
B61: =IF($I61="","",INDEX(Задачи!$A$1:$A$501,$I61)&"") | C61: =IF($I61="","",INDEX(Задачи!$B$1:$B$501,$I61)&"") | D61: =IF($I61="","",INDEX(Задачи!$C$1:$C$501,$I61)&"") | E61: =IF($I61="","",IF(INDEX(Задачи!$D$1:$D$501,$I61)="","Не начато",INDEX(Задачи!$D$1:$D$501,$I61))) | F61: =IF($I61="","",IF(INDEX(Задачи!$F$1:$F$501,$I61)="","",INDEX(Задачи!$F$1:$F$501,$I61))) | G61: =IF($I61="","",INDEX(Задачи!$K$1:$K$501,$I61)&"") | H61: =IF($I61="","",INDEX(Задачи!$I$1:$I$501,$I61)&"") | I61: =IFERROR(MOD(SMALL(Задачи!$O$2:$O$501,ROWS(I$58:I61)),1000),"")
B62: =IF($I62="","",INDEX(Задачи!$A$1:$A$501,$I62)&"") | C62: =IF($I62="","",INDEX(Задачи!$B$1:$B$501,$I62)&"") | D62: =IF($I62="","",INDEX(Задачи!$C$1:$C$501,$I62)&"") | E62: =IF($I62="","",IF(INDEX(Задачи!$D$1:$D$501,$I62)="","Не начато",INDEX(Задачи!$D$1:$D$501,$I62))) | F62: =IF($I62="","",IF(INDEX(Задачи!$F$1:$F$501,$I62)="","",INDEX(Задачи!$F$1:$F$501,$I62))) | G62: =IF($I62="","",INDEX(Задачи!$K$1:$K$501,$I62)&"") | H62: =IF($I62="","",INDEX(Задачи!$I$1:$I$501,$I62)&"") | I62: =IFERROR(MOD(SMALL(Задачи!$O$2:$O$501,ROWS(I$58:I62)),1000),"")
B63: =IF($I63="","",INDEX(Задачи!$A$1:$A$501,$I63)&"") | C63: =IF($I63="","",INDEX(Задачи!$B$1:$B$501,$I63)&"") | D63: =IF($I63="","",INDEX(Задачи!$C$1:$C$501,$I63)&"") | E63: =IF($I63="","",IF(INDEX(Задачи!$D$1:$D$501,$I63)="","Не начато",INDEX(Задачи!$D$1:$D$501,$I63))) | F63: =IF($I63="","",IF(INDEX(Задачи!$F$1:$F$501,$I63)="","",INDEX(Задачи!$F$1:$F$501,$I63))) | G63: =IF($I63="","",INDEX(Задачи!$K$1:$K$501,$I63)&"") | H63: =IF($I63="","",INDEX(Задачи!$I$1:$I$501,$I63)&"") | I63: =IFERROR(MOD(SMALL(Задачи!$O$2:$O$501,ROWS(I$58:I63)),1000),"")
B64: =IF($I64="","",INDEX(Задачи!$A$1:$A$501,$I64)&"") | C64: =IF($I64="","",INDEX(Задачи!$B$1:$B$501,$I64)&"") | D64: =IF($I64="","",INDEX(Задачи!$C$1:$C$501,$I64)&"") | E64: =IF($I64="","",IF(INDEX(Задачи!$D$1:$D$501,$I64)="","Не начато",INDEX(Задачи!$D$1:$D$501,$I64))) | F64: =IF($I64="","",IF(INDEX(Задачи!$F$1:$F$501,$I64)="","",INDEX(Задачи!$F$1:$F$501,$I64))) | G64: =IF($I64="","",INDEX(Задачи!$K$1:$K$501,$I64)&"") | H64: =IF($I64="","",INDEX(Задачи!$I$1:$I$501,$I64)&"") | I64: =IFERROR(MOD(SMALL(Задачи!$O$2:$O$501,ROWS(I$58:I64)),1000),"")
B65: =IF($I65="","",INDEX(Задачи!$A$1:$A$501,$I65)&"") | C65: =IF($I65="","",INDEX(Задачи!$B$1:$B$501,$I65)&"") | D65: =IF($I65="","",INDEX(Задачи!$C$1:$C$501,$I65)&"") | E65: =IF($I65="","",IF(INDEX(Задачи!$D$1:$D$501,$I65)="","Не начато",INDEX(Задачи!$D$1:$D$501,$I65))) | F65: =IF($I65="","",IF(INDEX(Задачи!$F$1:$F$501,$I65)="","",INDEX(Задачи!$F$1:$F$501,$I65))) | G65: =IF($I65="","",INDEX(Задачи!$K$1:$K$501,$I65)&"") | H65: =IF($I65="","",INDEX(Задачи!$I$1:$I$501,$I65)&"") | I65: =IFERROR(MOD(SMALL(Задачи!$O$2:$O$501,ROWS(I$58:I65)),1000),"")
B66: =IF($I66="","",INDEX(Задачи!$A$1:$A$501,$I66)&"") | C66: =IF($I66="","",INDEX(Задачи!$B$1:$B$501,$I66)&"") | D66: =IF($I66="","",INDEX(Задачи!$C$1:$C$501,$I66)&"") | E66: =IF($I66="","",IF(INDEX(Задачи!$D$1:$D$501,$I66)="","Не начато",INDEX(Задачи!$D$1:$D$501,$I66))) | F66: =IF($I66="","",IF(INDEX(Задачи!$F$1:$F$501,$I66)="","",INDEX(Задачи!$F$1:$F$501,$I66))) | G66: =IF($I66="","",INDEX(Задачи!$K$1:$K$501,$I66)&"") | H66: =IF($I66="","",INDEX(Задачи!$I$1:$I$501,$I66)&"") | I66: =IFERROR(MOD(SMALL(Задачи!$O$2:$O$501,ROWS(I$58:I66)),1000),"")
B67: =IF($I67="","",INDEX(Задачи!$A$1:$A$501,$I67)&"") | C67: =IF($I67="","",INDEX(Задачи!$B$1:$B$501,$I67)&"") | D67: =IF($I67="","",INDEX(Задачи!$C$1:$C$501,$I67)&"") | E67: =IF($I67="","",IF(INDEX(Задачи!$D$1:$D$501,$I67)="","Не начато",INDEX(Задачи!$D$1:$D$501,$I67))) | F67: =IF($I67="","",IF(INDEX(Задачи!$F$1:$F$501,$I67)="","",INDEX(Задачи!$F$1:$F$501,$I67))) | G67: =IF($I67="","",INDEX(Задачи!$K$1:$K$501,$I67)&"") | H67: =IF($I67="","",INDEX(Задачи!$I$1:$I$501,$I67)&"") | I67: =IFERROR(MOD(SMALL(Задачи!$O$2:$O$501,ROWS(I$58:I67)),1000),"")
B68: =IF($I68="","",INDEX(Задачи!$A$1:$A$501,$I68)&"") | C68: =IF($I68="","",INDEX(Задачи!$B$1:$B$501,$I68)&"") | D68: =IF($I68="","",INDEX(Задачи!$C$1:$C$501,$I68)&"") | E68: =IF($I68="","",IF(INDEX(Задачи!$D$1:$D$501,$I68)="","Не начато",INDEX(Задачи!$D$1:$D$501,$I68))) | F68: =IF($I68="","",IF(INDEX(Задачи!$F$1:$F$501,$I68)="","",INDEX(Задачи!$F$1:$F$501,$I68))) | G68: =IF($I68="","",INDEX(Задачи!$K$1:$K$501,$I68)&"") | H68: =IF($I68="","",INDEX(Задачи!$I$1:$I$501,$I68)&"") | I68: =IFERROR(MOD(SMALL(Задачи!$O$2:$O$501,ROWS(I$58:I68)),1000),"")
B69: =IF($I69="","",INDEX(Задачи!$A$1:$A$501,$I69)&"") | C69: =IF($I69="","",INDEX(Задачи!$B$1:$B$501,$I69)&"") | D69: =IF($I69="","",INDEX(Задачи!$C$1:$C$501,$I69)&"") | E69: =IF($I69="","",IF(INDEX(Задачи!$D$1:$D$501,$I69)="","Не начато",INDEX(Задачи!$D$1:$D$501,$I69))) | F69: =IF($I69="","",IF(INDEX(Задачи!$F$1:$F$501,$I69)="","",INDEX(Задачи!$F$1:$F$501,$I69))) | G69: =IF($I69="","",INDEX(Задачи!$K$1:$K$501,$I69)&"") | H69: =IF($I69="","",INDEX(Задачи!$I$1:$I$501,$I69)&"") | I69: =IFERROR(MOD(SMALL(Задачи!$O$2:$O$501,ROWS(I$58:I69)),1000),"")
B71: Выполненные задачи автоматически попадают на лист «Выполненные».

Sheet Задачи
A1: Задача | B1: Категория | C1: Приоритет | D1: Статус | E1: Дата постановки | F1: Срок | G1: Повтор | H1: Время | I1: Комментарий / результат | J1: Блок (авто) | K1: Срок: осталось (авто) | L1: Ключ | M1: Срочные | N1: Текущие | O1: Плановые | P1: Выполнено
A2: Проверить и улучшить объявление промбазы на Krisha.kz | B2: Промбаза | C2: Высокий | D2: Выполнено | G2: Еженедельно | H2: 30 мин | J2: =IF(TRIM(A2)="","",IF(D2="Выполнено","Выполнено",IF(OR(C2="Срочно",AND(F2<>"",F2<=TODAY())),"Срочные",IF(OR(D2="Отложено",C2="Низкий",AND(F2<>"",F2>TODAY()+Справочники!$H$2)),"Плановые","Текущие")))) -> Выполнено | K2: =IF(OR(A2="",D2="Выполнено"),"",IF(F2="",IF(AND(G2<>"",G2<>"Разово"),"↻ "&G2,""),IF(F2<TODAY(),"Просрочено на "&(TODAY()-F2)&" дн.",IF(F2=TODAY(),"Сегодня",IF(F2=TODAY()+1,"Завтра","Через "&(F2-TODAY())&" дн."))))) | L2: =IF(J2="","",(IF(AND(F2<>"",F2<TODAY()),0,1)*10000000+IFERROR(MATCH(C2,{"Срочно","Высокий","Средний","Низкий"},0),5)*100000+IF(F2="",99999,F2))*1000+ROW()) -> 10299999002 | M2: =IF(AND($J2="Срочные",OR(Главная!$F$6="Все",$B2=Главная!$F$6),OR(Главная!$F$7="Все",$C2=Главная!$F$7)),$L2,"") | N2: =IF(AND($J2="Текущие",OR(Главная!$F$6="Все",$B2=Главная!$F$6),OR(Главная!$F$7="Все",$C2=Главная!$F$7)),$L2,"") | O2: =IF(AND($J2="Плановые",OR(Главная!$F$6="Все",$B2=Главная!$F$6),OR(Главная!$F$7="Все",$C2=Главная!$F$7)),$L2,"") | P2: =IF(J2="Выполнено",ROW(),"") -> 2
A3: Разместить / обновить объявление на Krisha.kz по промбазе / по Таргету | B3: Промбаза | C3: Высокий | D3: Выполнено | F3: 46301 | G3: Разово | H3: 30–45 мин | J3: =IF(TRIM(A3)="","",IF(D3="Выполнено","Выполнено",IF(OR(C3="Срочно",AND(F3<>"",F3<=TODAY())),"Срочные",IF(OR(D3="Отложено",C3="Низкий",AND(F3<>"",F3>TODAY()+Справочники!$H$2)),"Плановые","Текущие")))) -> Выполнено | K3: =IF(OR(A3="",D3="Выполнено"),"",IF(F3="",IF(AND(G3<>"",G3<>"Разово"),"↻ "&G3,""),IF(F3<TODAY(),"Просрочено на "&(TODAY()-F3)&" дн.",IF(F3=TODAY(),"Сегодня",IF(F3=TODAY()+1,"Завтра","Через "&(F3-TODAY())&" дн."))))) | L3: =IF(J3="","",(IF(AND(F3<>"",F3<TODAY()),0,1)*10000000+IFERROR(MATCH(C3,{"Срочно","Высокий","Средний","Низкий"},0),5)*100000+IF(F3="",99999,F3))*1000+ROW()) -> 10246301003 | M3: =IF(AND($J3="Срочные",OR(Главная!$F$6="Все",$B3=Главная!$F$6),OR(Главная!$F$7="Все",$C3=Главная!$F$7)),$L3,"") | N3: =IF(AND($J3="Текущие",OR(Главная!$F$6="Все",$B3=Главная!$F$6),OR(Главная!$F$7="Все",$C3=Главная!$F$7)),$L3,"") | O3: =IF(AND($J3="Плановые",OR(Главная!$F$6="Все",$B3=Главная!$F$6),OR(Главная!$F$7="Все",$C3=Главная!$F$7)),$L3,"") | P3: =IF(J3="Выполнено",ROW(),"") -> 3
A4: Контролировать таргет по промбазе: заявки, стоимость лида, качество обращений | B4: Промбаза / маркетинг | C4: Высокий | D4: В работе | G4: Ежедневно | H4: 20–30 мин | J4: =IF(TRIM(A4)="","",IF(D4="Выполнено","Выполнено",IF(OR(C4="Срочно",AND(F4<>"",F4<=TODAY())),"Срочные",IF(OR(D4="Отложено",C4="Низкий",AND(F4<>"",F4>TODAY()+Справочники!$H$2)),"Плановые","Текущие")))) -> Текущие | K4: =IF(OR(A4="",D4="Выполнено"),"",IF(F4="",IF(AND(G4<>"",G4<>"Разово"),"↻ "&G4,""),IF(F4<TODAY(),"Просрочено на "&(TODAY()-F4)&" дн.",IF(F4=TODAY(),"Сегодня",IF(F4=TODAY()+1,"Завтра","Через "&(F4-TODAY())&" дн."))))) -> ↻ Ежедневно | L4: =IF(J4="","",(IF(AND(F4<>"",F4<TODAY()),0,1)*10000000+IFERROR(MATCH(C4,{"Срочно","Высокий","Средний","Низкий"},0),5)*100000+IF(F4="",99999,F4))*1000+ROW()) -> 10299999004 | M4: =IF(AND($J4="Срочные",OR(Главная!$F$6="Все",$B4=Главная!$F$6),OR(Главная!$F$7="Все",$C4=Главная!$F$7)),$L4,"") | N4: =IF(AND($J4="Текущие",OR(Главная!$F$6="Все",$B4=Главная!$F$6),OR(Главная!$F$7="Все",$C4=Главная!$F$7)),$L4,"") -> 10299999004 | O4: =IF(AND($J4="Плановые",OR(Главная!$F$6="Все",$B4=Главная!$F$6),OR(Главная!$F$7="Все",$C4=Главная!$F$7)),$L4,"") | P4: =IF(J4="Выполнено",ROW(),"")
A5: Поиск сотрудника — приёмщик | B5: Найм | C5: Высокий | D5: В работе | G5: Ежедневно | H5: 45 мин | I5: подала объявление в НН, Каспи Периодичность: ежедневно до закрытия | J5: =IF(TRIM(A5)="","",IF(D5="Выполнено","Выполнено",IF(OR(C5="Срочно",AND(F5<>"",F5<=TODAY())),"Срочные",IF(OR(D5="Отложено",C5="Низкий",AND(F5<>"",F5>TODAY()+Справочники!$H$2)),"Плановые","Текущие")))) -> Текущие | K5: =IF(OR(A5="",D5="Выполнено"),"",IF(F5="",IF(AND(G5<>"",G5<>"Разово"),"↻ "&G5,""),IF(F5<TODAY(),"Просрочено на "&(TODAY()-F5)&" дн.",IF(F5=TODAY(),"Сегодня",IF(F5=TODAY()+1,"Завтра","Через "&(F5-TODAY())&" дн."))))) -> ↻ Ежедневно | L5: =IF(J5="","",(IF(AND(F5<>"",F5<TODAY()),0,1)*10000000+IFERROR(MATCH(C5,{"Срочно","Высокий","Средний","Низкий"},0),5)*100000+IF(F5="",99999,F5))*1000+ROW()) -> 10299999005 | M5: =IF(AND($J5="Срочные",OR(Главная!$F$6="Все",$B5=Главная!$F$6),OR(Главная!$F$7="Все",$C5=Главная!$F$7)),$L5,"") | N5: =IF(AND($J5="Текущие",OR(Главная!$F$6="Все",$B5=Главная!$F$6),OR(Главная!$F$7="Все",$C5=Главная!$F$7)),$L5,"") -> 10299999005 | O5: =IF(AND($J5="Плановые",OR(Главная!$F$6="Все",$B5=Главная!$F$6),OR(Главная!$F$7="Все",$C5=Главная!$F$7)),$L5,"") | P5: =IF(J5="Выполнено",ROW(),"")
A6: Поиск SMM-специалиста | B6: Найм | C6: Высокий | D6: В работе | G6: Ежедневно | H6: 45 мин | I6: Периодичность: ежедневно до закрытия | J6: =IF(TRIM(A6)="","",IF(D6="Выполнено","Выполнено",IF(OR(C6="Срочно",AND(F6<>"",F6<=TODAY())),"Срочные",IF(OR(D6="Отложено",C6="Низкий",AND(F6<>"",F6>TODAY()+Справочники!$H$2)),"Плановые","Текущие")))) -> Текущие | K6: =IF(OR(A6="",D6="Выполнено"),"",IF(F6="",IF(AND(G6<>"",G6<>"Разово"),"↻ "&G6,""),IF(F6<TODAY(),"Просрочено на "&(TODAY()-F6)&" дн.",IF(F6=TODAY(),"Сегодня",IF(F6=TODAY()+1,"Завтра","Через "&(F6-TODAY())&" дн."))))) -> ↻ Ежедневно | L6: =IF(J6="","",(IF(AND(F6<>"",F6<TODAY()),0,1)*10000000+IFERROR(MATCH(C6,{"Срочно","Высокий","Средний","Низкий"},0),5)*100000+IF(F6="",99999,F6))*1000+ROW()) -> 10299999006 | M6: =IF(AND($J6="Срочные",OR(Главная!$F$6="Все",$B6=Главная!$F$6),OR(Главная!$F$7="Все",$C6=Главная!$F$7)),$L6,"") | N6: =IF(AND($J6="Текущие",OR(Главная!$F$6="Все",$B6=Главная!$F$6),OR(Главная!$F$7="Все",$C6=Главная!$F$7)),$L6,"") -> 10299999006 | O6: =IF(AND($J6="Плановые",OR(Главная!$F$6="Все",$B6=Главная!$F$6),OR(Главная!$F$7="Все",$C6=Главная!$F$7)),$L6,"") | P6: =IF(J6="Выполнено",ROW(),"")
A7: Поиск торгового менеджера | B7: Найм | C7: Высокий | D7: Не начато | G7: Ежедневно | H7: 30 мин | I7: Шеф: 200 оклад, план на 10 млн -1% от продаж, график 6/1 , 100 тыс дорожный + обед | J7: =IF(TRIM(A7)="","",IF(D7="Выполнено","Выполнено",IF(OR(C7="Срочно",AND(F7<>"",F7<=TODAY())),"Срочные",IF(OR(D7="Отложено",C7="Низкий",AND(F7<>"",F7>TODAY()+Справочники!$H$2)),"Плановые","Текущие")))) -> Текущие | K7: =IF(OR(A7="",D7="Выполнено"),"",IF(F7="",IF(AND(G7<>"",G7<>"Разово"),"↻ "&G7,""),IF(F7<TODAY(),"Просрочено на "&(TODAY()-F7)&" дн.",IF(F7=TODAY(),"Сегодня",IF(F7=TODAY()+1,"Завтра","Через "&(F7-TODAY())&" дн."))))) -> ↻ Ежедневно | L7: =IF(J7="","",(IF(AND(F7<>"",F7<TODAY()),0,1)*10000000+IFERROR(MATCH(C7,{"Срочно","Высокий","Средний","Низкий"},0),5)*100000+IF(F7="",99999,F7))*1000+ROW()) -> 10299999007 | M7: =IF(AND($J7="Срочные",OR(Главная!$F$6="Все",$B7=Главная!$F$6),OR(Главная!$F$7="Все",$C7=Главная!$F$7)),$L7,"") | N7: =IF(AND($J7="Текущие",OR(Главная!$F$6="Все",$B7=Главная!$F$6),OR(Главная!$F$7="Все",$C7=Главная!$F$7)),$L7,"") -> 10299999007 | O7: =IF(AND($J7="Плановые",OR(Главная!$F$6="Все",$B7=Главная!$F$6),OR(Главная!$F$7="Все",$C7=Главная!$F$7)),$L7,"") | P7: =IF(J7="Выполнено",ROW(),"")
A8: Поиск регионального менеджера | B8: Найм | C8: Высокий | D8: Не начато | G8: Ежедневно | H8: 45 мин | I8: Периодичность: ежедневно до закрытия | J8: =IF(TRIM(A8)="","",IF(D8="Выполнено","Выполнено",IF(OR(C8="Срочно",AND(F8<>"",F8<=TODAY())),"Срочные",IF(OR(D8="Отложено",C8="Низкий",AND(F8<>"",F8>TODAY()+Справочники!$H$2)),"Плановые","Текущие")))) -> Текущие | K8: =IF(OR(A8="",D8="Выполнено"),"",IF(F8="",IF(AND(G8<>"",G8<>"Разово"),"↻ "&G8,""),IF(F8<TODAY(),"Просрочено на "&(TODAY()-F8)&" дн.",IF(F8=TODAY(),"Сегодня",IF(F8=TODAY()+1,"Завтра","Через "&(F8-TODAY())&" дн."))))) -> ↻ Ежедневно | L8: =IF(J8="","",(IF(AND(F8<>"",F8<TODAY()),0,1)*10000000+IFERROR(MATCH(C8,{"Срочно","Высокий","Средний","Низкий"},0),5)*100000+IF(F8="",99999,F8))*1000+ROW()) -> 10299999008 | M8: =IF(AND($J8="Срочные",OR(Главная!$F$6="Все",$B8=Главная!$F$6),OR(Главная!$F$7="Все",$C8=Главная!$F$7)),$L8,"") | N8: =IF(AND($J8="Текущие",OR(Главная!$F$6="Все",$B8=Главная!$F$6),OR(Главная!$F$7="Все",$C8=Главная!$F$7)),$L8,"") -> 10299999008 | O8: =IF(AND($J8="Плановые",OR(Главная!$F$6="Все",$B8=Главная!$F$6),OR(Главная!$F$7="Все",$C8=Главная!$F$7)),$L8,"") | P8: =IF(J8="Выполнено",ROW(),"")
A9: Поиск маркетолога | B9: Найм | C9: Высокий | D9: Выполнено | F9: 46301 | G9: Разово | H9: 45 мин | I9: ждем ответа с 12 го октября выйдет на работу | J9: =IF(TRIM(A9)="","",IF(D9="Выполнено","Выполнено",IF(OR(C9="Срочно",AND(F9<>"",F9<=TODAY())),"Срочные",IF(OR(D9="Отложено",C9="Низкий",AND(F9<>"",F9>TODAY()+Справочники!$H$2)),"Плановые","Текущие")))) -> Выполнено | K9: =IF(OR(A9="",D9="Выполнено"),"",IF(F9="",IF(AND(G9<>"",G9<>"Разово"),"↻ "&G9,""),IF(F9<TODAY(),"Просрочено на "&(TODAY()-F9)&" дн.",IF(F9=TODAY(),"Сегодня",IF(F9=TODAY()+1,"Завтра","Через "&(F9-TODAY())&" дн."))))) | L9: =IF(J9="","",(IF(AND(F9<>"",F9<TODAY()),0,1)*10000000+IFERROR(MATCH(C9,{"Срочно","Высокий","Средний","Низкий"},0),5)*100000+IF(F9="",99999,F9))*1000+ROW()) -> 10246301009 | M9: =IF(AND($J9="Срочные",OR(Главная!$F$6="Все",$B9=Главная!$F$6),OR(Главная!$F$7="Все",$C9=Главная!$F$7)),$L9,"") | N9: =IF(AND($J9="Текущие",OR(Главная!$F$6="Все",$B9=Главная!$F$6),OR(Главная!$F$7="Все",$C9=Главная!$F$7)),$L9,"") | O9: =IF(AND($J9="Плановые",OR(Главная!$F$6="Все",$B9=Главная!$F$6),OR(Главная!$F$7="Все",$C9=Главная!$F$7)),$L9,"") | P9: =IF(J9="Выполнено",ROW(),"") -> 9
A10: Продвижение подгузников: идеи, контент, каналы продвижения, контроль,Посик UGS креаторов, блогеров | B10: Подгузники / маркетинг | C10: Высокий | D10: Отложено | G10: Ежедневно | H10: 1 час | I10: совместо с маркетологом будем работать | J10: =IF(TRIM(A10)="","",IF(D10="Выполнено","Выполнено",IF(OR(C10="Срочно",AND(F10<>"",F10<=TODAY())),"Срочные",IF(OR(D10="Отложено",C10="Низкий",AND(F10<>"",F10>TODAY()+Справочники!$H$2)),"Плановые","Текущие")))) -> Плановые | K10: =IF(OR(A10="",D10="Выполнено"),"",IF(F10="",IF(AND(G10<>"",G10<>"Разово"),"↻ "&G10,""),IF(F10<TODAY(),"Просрочено на "&(TODAY()-F10)&" дн.",IF(F10=TODAY(),"Сегодня",IF(F10=TODAY()+1,"Завтра","Через "&(F10-TODAY())&" дн."))))) -> ↻ Ежедневно | L10: =IF(J10="","",(IF(AND(F10<>"",F10<TODAY()),0,1)*10000000+IFERROR(MATCH(C10,{"Срочно","Высокий","Средний","Низкий"},0),5)*100000+IF(F10="",99999,F10))*1000+ROW()) -> 10299999010 | M10: =IF(AND($J10="Срочные",OR(Главная!$F$6="Все",$B10=Главная!$F$6),OR(Главная!$F$7="Все",$C10=Главная!$F$7)),$L10,"") | N10: =IF(AND($J10="Текущие",OR(Главная!$F$6="Все",$B10=Главная!$F$6),OR(Главная!$F$7="Все",$C10=Главная!$F$7)),$L10,"") | O10: =IF(AND($J10="Плановые",OR(Главная!$F$6="Все",$B10=Главная!$F$6),OR(Главная!$F$7="Все",$C10=Главная!$F$7)),$L10,"") -> 10299999010 | P10: =IF(J10="Выполнено",ROW(),"")
A11: Закончить регламент сотрудников | B11: Управление | C11: Срочно | D11: В работе | F11: 46301 | G11: Разово | H11: 1–2 часа | I11: в трудовом договоре указать налогии | J11: =IF(TRIM(A11)="","",IF(D11="Выполнено","Выполнено",IF(OR(C11="Срочно",AND(F11<>"",F11<=TODAY())),"Срочные",IF(OR(D11="Отложено",C11="Низкий",AND(F11<>"",F11>TODAY()+Справочники!$H$2)),"Плановые","Текущие")))) -> Срочные | K11: =IF(OR(A11="",D11="Выполнено"),"",IF(F11="",IF(AND(G11<>"",G11<>"Разово"),"↻ "&G11,""),IF(F11<TODAY(),"Просрочено на "&(TODAY()-F11)&" дн.",IF(F11=TODAY(),"Сегодня",IF(F11=TODAY()+1,"Завтра","Через "&(F11-TODAY())&" дн."))))) -> Сегодня | L11: =IF(J11="","",(IF(AND(F11<>"",F11<TODAY()),0,1)*10000000+IFERROR(MATCH(C11,{"Срочно","Высокий","Средний","Низкий"},0),5)*100000+IF(F11="",99999,F11))*1000+ROW()) -> 10146301011 | M11: =IF(AND($J11="Срочные",OR(Главная!$F$6="Все",$B11=Главная!$F$6),OR(Главная!$F$7="Все",$C11=Главная!$F$7)),$L11,"") -> 10146301011 | N11: =IF(AND($J11="Текущие",OR(Главная!$F$6="Все",$B11=Главная!$F$6),OR(Главная!$F$7="Все",$C11=Главная!$F$7)),$L11,"") | O11: =IF(AND($J11="Плановые",OR(Главная!$F$6="Все",$B11=Главная!$F$6),OR(Главная!$F$7="Все",$C11=Главная!$F$7)),$L11,"") | P11: =IF(J11="Выполнено",ROW(),"")
A12: Закончить мотивационную систему сотрудников | B12: Продажи / управление | C12: Срочно | D12: Выполнено | F12: 46301 | G12: Разово | H12: 1–2 часа | J12: =IF(TRIM(A12)="","",IF(D12="Выполнено","Выполнено",IF(OR(C12="Срочно",AND(F12<>"",F12<=TODAY())),"Срочные",IF(OR(D12="Отложено",C12="Низкий",AND(F12<>"",F12>TODAY()+Справочники!$H$2)),"Плановые","Текущие")))) -> Выполнено | K12: =IF(OR(A12="",D12="Выполнено"),"",IF(F12="",IF(AND(G12<>"",G12<>"Разово"),"↻ "&G12,""),IF(F12<TODAY(),"Просрочено на "&(TODAY()-F12)&" дн.",IF(F12=TODAY(),"Сегодня",IF(F12=TODAY()+1,"Завтра","Через "&(F12-TODAY())&" дн."))))) | L12: =IF(J12="","",(IF(AND(F12<>"",F12<TODAY()),0,1)*10000000+IFERROR(MATCH(C12,{"Срочно","Высокий","Средний","Низкий"},0),5)*100000+IF(F12="",99999,F12))*1000+ROW()) -> 10146301012 | M12: =IF(AND($J12="Срочные",OR(Главная!$F$6="Все",$B12=Главная!$F$6),OR(Главная!$F$7="Все",$C12=Главная!$F$7)),$L12,"") | N12: =IF(AND($J12="Текущие",OR(Главная!$F$6="Все",$B12=Главная!$F$6),OR(Главная!$F$7="Все",$C12=Главная!$F$7)),$L12,"") | O12: =IF(AND($J12="Плановые",OR(Главная!$F$6="Все",$B12=Главная!$F$6),OR(Главная!$F$7="Все",$C12=Главная!$F$7)),$L12,"") | P12: =IF(J12="Выполнено",ROW(),"") -> 12
A13: Съездить в общежитие и снять фото/видео и зикр выставять обьяв | B13: Недвижимость | C13: Средний | D13: Не начато | F13: 46301 | G13: Разово | H13: 1–2 часа | J13: =IF(TRIM(A13)="","",IF(D13="Выполнено","Выполнено",IF(OR(C13="Срочно",AND(F13<>"",F13<=TODAY())),"Срочные",IF(OR(D13="Отложено",C13="Низкий",AND(F13<>"",F13>TODAY()+Справочники!$H$2)),"Плановые","Текущие")))) -> Срочные | K13: =IF(OR(A13="",D13="Выполнено"),"",IF(F13="",IF(AND(G13<>"",G13<>"Разово"),"↻ "&G13,""),IF(F13<TODAY(),"Просрочено на "&(TODAY()-F13)&" дн.",IF(F13=TODAY(),"Сегодня",IF(F13=TODAY()+1,"Завтра","Через "&(F13-TODAY())&" дн."))))) -> Сегодня | L13: =IF(J13="","",(IF(AND(F13<>"",F13<TODAY()),0,1)*10000000+IFERROR(MATCH(C13,{"Срочно","Высокий","Средний","Низкий"},0),5)*100000+IF(F13="",99999,F13))*1000+ROW()) -> 10346301013 | M13: =IF(AND($J13="Срочные",OR(Главная!$F$6="Все",$B13=Главная!$F$6),OR(Главная!$F$7="Все",$C13=Главная!$F$7)),$L13,"") -> 10346301013 | N13: =IF(AND($J13="Текущие",OR(Главная!$F$6="Все",$B13=Главная!$F$6),OR(Главная!$F$7="Все",$C13=Главная!$F$7)),$L13,"") | O13: =IF(AND($J13="Плановые",OR(Главная!$F$6="Все",$B13=Главная!$F$6),OR(Главная!$F$7="Все",$C13=Главная!$F$7)),$L13,"") | P13: =IF(J13="Выполнено",ROW(),"")
A14: Разместить общежитие на Krisha.kz после съёмки | B14: Недвижимость | C14: Средний | D14: Не начато | F14: 46302 | G14: Разово | H14: 30–45 мин | J14: =IF(TRIM(A14)="","",IF(D14="Выполнено","Выполнено",IF(OR(C14="Срочно",AND(F14<>"",F14<=TODAY())),"Срочные",IF(OR(D14="Отложено",C14="Низкий",AND(F14<>"",F14>TODAY()+Справочники!$H$2)),"Плановые","Текущие")))) -> Текущие | K14: =IF(OR(A14="",D14="Выполнено"),"",IF(F14="",IF(AND(G14<>"",G14<>"Разово"),"↻ "&G14,""),IF(F14<TODAY(),"Просрочено на "&(TODAY()-F14)&" дн.",IF(F14=TODAY(),"Сегодня",IF(F14=TODAY()+1,"Завтра","Через "&(F14-TODAY())&" дн."))))) -> Завтра | L14: =IF(J14="","",(IF(AND(F14<>"",F14<TODAY()),0,1)*10000000+IFERROR(MATCH(C14,{"Срочно","Высокий","Средний","Низкий"},0),5)*100000+IF(F14="",99999,F14))*1000+ROW()) -> 10346302014 | M14: =IF(AND($J14="Срочные",OR(Главная!$F$6="Все",$B14=Главная!$F$6),OR(Главная!$F$7="Все",$C14=Главная!$F$7)),$L14,"") | N14: =IF(AND($J14="Текущие",OR(Главная!$F$6="Все",$B14=Главная!$F$6),OR(Главная!$F$7="Все",$C14=Главная!$F$7)),$L14,"") -> 10346302014 | O14: =IF(AND($J14="Плановые",OR(Главная!$F$6="Все",$B14=Главная!$F$6),OR(Главная!$F$7="Все",$C14=Главная!$F$7)),$L14,"") | P14: =IF(J14="Выполнено",ROW(),"")
A15: Паспорт Объекта | B15: Оптовка | C15: Средний | D15: Не начато | F15: 46302 | G15: Разово | H15: 15 мин | I15: Регина Улан | J15: =IF(TRIM(A15)="","",IF(D15="Выполнено","Выполнено",IF(OR(C15="Срочно",AND(F15<>"",F15<=TODAY())),"Срочные",IF(OR(D15="Отложено",C15="Низкий",AND(F15<>"",F15>TODAY()+Справочники!$H$2)),"Плановые","Текущие")))) -> Текущие | K15: =IF(OR(A15="",D15="Выполнено"),"",IF(F15="",IF(AND(G15<>"",G15<>"Разово"),"↻ "&G15,""),IF(F15<TODAY(),"Просрочено на "&(TODAY()-F15)&" дн.",IF(F15=TODAY(),"Сегодня",IF(F15=TODAY()+1,"Завтра","Через "&(F15-TODAY())&" дн."))))) -> Завтра | L15: =IF(J15="","",(IF(AND(F15<>"",F15<TODAY()),0,1)*10000000+IFERROR(MATCH(C15,{"Срочно","Высокий","Средний","Низкий"},0),5)*100000+IF(F15="",99999,F15))*1000+ROW()) -> 10346302015 | M15: =IF(AND($J15="Срочные",OR(Главная!$F$6="Все",$B15=Главная!$F$6),OR(Главная!$F$7="Все",$C15=Главная!$F$7)),$L15,"") | N15: =IF(AND($J15="Текущие",OR(Главная!$F$6="Все",$B15=Главная!$F$6),OR(Главная!$F$7="Все",$C15=Главная!$F$7)),$L15,"") -> 10346302015 | O15: =IF(AND($J15="Плановые",OR(Главная!$F$6="Все",$B15=Главная!$F$6),OR(Главная!$F$7="Все",$C15=Главная!$F$7)),$L15,"") | P15: =IF(J15="Выполнено",ROW(),"")
A16: Пожарная безопасность | B16: Оптовка | C16: Высокий | D16: В работе | F16: 46301 | G16: Разово | H16: 45 мин | I16: вопрос делегирован Улжану | J16: =IF(TRIM(A16)="","",IF(D16="Выполнено","Выполнено",IF(OR(C16="Срочно",AND(F16<>"",F16<=TODAY())),"Срочные",IF(OR(D16="Отложено",C16="Низкий",AND(F16<>"",F16>TODAY()+Справочники!$H$2)),"Плановые","Текущие")))) -> Срочные | K16: =IF(OR(A16="",D16="Выполнено"),"",IF(F16="",IF(AND(G16<>"",G16<>"Разово"),"↻ "&G16,""),IF(F16<TODAY(),"Просрочено на "&(TODAY()-F16)&" дн.",IF(F16=TODAY(),"Сегодня",IF(F16=TODAY()+1,"Завтра","Через "&(F16-TODAY())&" дн."))))) -> Сегодня | L16: =IF(J16="","",(IF(AND(F16<>"",F16<TODAY()),0,1)*10000000+IFERROR(MATCH(C16,{"Срочно","Высокий","Средний","Низкий"},0),5)*100000+IF(F16="",99999,F16))*1000+ROW()) -> 10246301016 | M16: =IF(AND($J16="Срочные",OR(Главная!$F$6="Все",$B16=Главная!$F$6),OR(Главная!$F$7="Все",$C16=Главная!$F$7)),$L16,"") -> 10246301016 | N16: =IF(AND($J16="Текущие",OR(Главная!$F$6="Все",$B16=Главная!$F$6),OR(Главная!$F$7="Все",$C16=Главная!$F$7)),$L16,"") | O16: =IF(AND($J16="Плановые",OR(Главная!$F$6="Все",$B16=Главная!$F$6),OR(Главная!$F$7="Все",$C16=Главная!$F$7)),$L16,"") | P16: =IF(J16="Выполнено",ROW(),"")
A17: Страхование компаний ТМЦ, надо найти компании, от Гульзиры бух спросить анкету | B17: Управление | C17: Срочно | D17: Выполнено | F17: 46302 | G17: Разово | H17: 30 мин | I17: приедут две компании на осмотр объекта сегодня Шеф: ждем ответ от Евразия Номад Аманат КП, до Халыка не дозвонилась | J17: =IF(TRIM(A17)="","",IF(D17="Выполнено","Выполнено",IF(OR(C17="Срочно",AND(F17<>"",F17<=TODAY())),"Срочные",IF(OR(D17="Отложено",C17="Низкий",AND(F17<>"",F17>TODAY()+Справочники!$H$2)),"Плановые","Текущие")))) -> Выполнено | K17: =IF(OR(A17="",D17="Выполнено"),"",IF(F17="",IF(AND(G17<>"",G17<>"Разово"),"↻ "&G17,""),IF(F17<TODAY(),"Просрочено на "&(TODAY()-F17)&" дн.",IF(F17=TODAY(),"Сегодня",IF(F17=TODAY()+1,"Завтра","Через "&(F17-TODAY())&" дн."))))) | L17: =IF(J17="","",(IF(AND(F17<>"",F17<TODAY()),0,1)*10000000+IFERROR(MATCH(C17,{"Срочно","Высокий","Средний","Низкий"},0),5)*100000+IF(F17="",99999,F17))*1000+ROW()) -> 10146302017 | M17: =IF(AND($J17="Срочные",OR(Главная!$F$6="Все",$B17=Главная!$F$6),OR(Главная!$F$7="Все",$C17=Главная!$F$7)),$L17,"") | N17: =IF(AND($J17="Текущие",OR(Главная!$F$6="Все",$B17=Главная!$F$6),OR(Главная!$F$7="Все",$C17=Главная!$F$7)),$L17,"") | O17: =IF(AND($J17="Плановые",OR(Главная!$F$6="Все",$B17=Главная!$F$6),OR(Главная!$F$7="Все",$C17=Главная!$F$7)),$L17,"") | P17: =IF(J17="Выполнено",ROW(),"") -> 17
A18: Страхование жизни уточнить взять КП | B18: Управление | D18: Не начато | G18: Разово | J18: =IF(TRIM(A18)="","",IF(D18="Выполнено","Выполнено",IF(OR(C18="Срочно",AND(F18<>"",F18<=TODAY())),"Срочные",IF(OR(D18="Отложено",C18="Низкий",AND(F18<>"",F18>TODAY()+Справочники!$H$2)),"Плановые","Текущие")))) -> Текущие | K18: =IF(OR(A18="",D18="Выполнено"),"",IF(F18="",IF(AND(G18<>"",G18<>"Разово"),"↻ "&G18,""),IF(F18<TODAY(),"Просрочено на "&(TODAY()-F18)&" дн.",IF(F18=TODAY(),"Сегодня",IF(F18=TODAY()+1,"Завтра","Через "&(F18-TODAY())&" дн."))))) | L18: =IF(J18="","",(IF(AND(F18<>"",F18<TODAY()),0,1)*10000000+IFERROR(MATCH(C18,{"Срочно","Высокий","Средний","Низкий"},0),5)*100000+IF(F18="",99999,F18))*1000+ROW()) -> 10599999018 | M18: =IF(AND($J18="Срочные",OR(Главная!$F$6="Все",$B18=Главная!$F$6),OR(Главная!$F$7="Все",$C18=Главная!$F$7)),$L18,"") | N18: =IF(AND($J18="Текущие",OR(Главная!$F$6="Все",$B18=Главная!$F$6),OR(Главная!$F$7="Все",$C18=Главная!$F$7)),$L18,"") -> 10599999018 | O18: =IF(AND($J18="Плановые",OR(Главная!$F$6="Все",$B18=Главная!$F$6),OR(Главная!$F$7="Все",$C18=Главная!$F$7)),$L18,"") | P18: =IF(J18="Выполнено",ROW(),"")
A19: Даулет мырза набрать, напомнить,Улжана передать на поле | B19: Оптовка | C19: Средний | D19: Ожидает | F19: 46301 | G19: Разово | H19: 2–3 часа | J19: =IF(TRIM(A19)="","",IF(D19="Выполнено","Выполнено",IF(OR(C19="Срочно",AND(F19<>"",F19<=TODAY())),"Срочные",IF(OR(D19="Отложено",C19="Низкий",AND(F19<>"",F19>TODAY()+Справочники!$H$2)),"Плановые","Текущие")))) -> Срочные | K19: =IF(OR(A19="",D19="Выполнено"),"",IF(F19="",IF(AND(G19<>"",G19<>"Разово"),"↻ "&G19,""),IF(F19<TODAY(),"Просрочено на "&(TODAY()-F19)&" дн.",IF(F19=TODAY(),"Сегодня",IF(F19=TODAY()+1,"Завтра","Через "&(F19-TODAY())&" дн."))))) -> Сегодня | L19: =IF(J19="","",(IF(AND(F19<>"",F19<TODAY()),0,1)*10000000+IFERROR(MATCH(C19,{"Срочно","Высокий","Средний","Низкий"},0),5)*100000+IF(F19="",99999,F19))*1000+ROW()) -> 10346301019 | M19: =IF(AND($J19="Срочные",OR(Главная!$F$6="Все",$B19=Главная!$F$6),OR(Главная!$F$7="Все",$C19=Главная!$F$7)),$L19,"") -> 10346301019 | N19: =IF(AND($J19="Текущие",OR(Главная!$F$6="Все",$B19=Главная!$F$6),OR(Главная!$F$7="Все",$C19=Главная!$F$7)),$L19,"") | O19: =IF(AND($J19="Плановые",OR(Главная!$F$6="Все",$B19=Главная!$F$6),OR(Главная!$F$7="Все",$C19=Главная!$F$7)),$L19,"") | P19: =IF(J19="Выполнено",ROW(),"")
A20: Зарегистровать компанию в портал Алеумет | B20: Подгузники / маркетинг | C20: Высокий | D20: Не начато | F20: 46304 | G20: Разово | H20: 1 час | I20: эцп,декларация о соответствии подтв соответсвия, регистрационное удостоверение, док сертификат, регистрационные дркументы, сведение о товаре цена ,все данные компании ТОО,запросить у Гульжайны, | J20: =IF(TRIM(A20)="","",IF(D20="Выполнено","Выполнено",IF(OR(C20="Срочно",AND(F20<>"",F20<=TODAY())),"Срочные",IF(OR(D20="Отложено",C20="Низкий",AND(F20<>"",F20>TODAY()+Справочники!$H$2)),"Плановые","Текущие")))) -> Текущие | K20: =IF(OR(A20="",D20="Выполнено"),"",IF(F20="",IF(AND(G20<>"",G20<>"Разово"),"↻ "&G20,""),IF(F20<TODAY(),"Просрочено на "&(TODAY()-F20)&" дн.",IF(F20=TODAY(),"Сегодня",IF(F20=TODAY()+1,"Завтра","Через "&(F20-TODAY())&" дн."))))) -> Через 3 дн. | L20: =IF(J20="","",(IF(AND(F20<>"",F20<TODAY()),0,1)*10000000+IFERROR(MATCH(C20,{"Срочно","Высокий","Средний","Низкий"},0),5)*100000+IF(F20="",99999,F20))*1000+ROW()) -> 10246304020 | M20: =IF(AND($J20="Срочные",OR(Главная!$F$6="Все",$B20=Главная!$F$6),OR(Главная!$F$7="Все",$C20=Главная!$F$7)),$L20,"") | N20: =IF(AND($J20="Текущие",OR(Главная!$F$6="Все",$B20=Главная!$F$6),OR(Главная!$F$7="Все",$C20=Главная!$F$7)),$L20,"") -> 10246304020 | O20: =IF(AND($J20="Плановые",OR(Главная!$F$6="Все",$B20=Главная!$F$6),OR(Главная!$F$7="Все",$C20=Главная!$F$7)),$L20,"") | P20: =IF(J20="Выполнено",ROW(),"")
A21: Решить вопрос по Алтел, сделать с компанией доп соглашение,купить тариф,заменить все старые номера | B21: Управление | C21: Срочно | D21: Выполнено | F21: 46301 | G21: Разово | J21: =IF(TRIM(A21)="","",IF(D21="Выполнено","Выполнено",IF(OR(C21="Срочно",AND(F21<>"",F21<=TODAY())),"Срочные",IF(OR(D21="Отложено",C21="Низкий",AND(F21<>"",F21>TODAY()+Справочники!$H$2)),"Плановые","Текущие")))) -> Выполнено | K21: =IF(OR(A21="",D21="Выполнено"),"",IF(F21="",IF(AND(G21<>"",G21<>"Разово"),"↻ "&G21,""),IF(F21<TODAY(),"Просрочено на "&(TODAY()-F21)&" дн.",IF(F21=TODAY(),"Сегодня",IF(F21=TODAY()+1,"Завтра","Через "&(F21-TODAY())&" дн."))))) | L21: =IF(J21="","",(IF(AND(F21<>"",F21<TODAY()),0,1)*10000000+IFERROR(MATCH(C21,{"Срочно","Высокий","Средний","Низкий"},0),5)*100000+IF(F21="",99999,F21))*1000+ROW()) -> 10146301021 | M21: =IF(AND($J21="Срочные",OR(Главная!$F$6="Все",$B21=Главная!$F$6),OR(Главная!$F$7="Все",$C21=Главная!$F$7)),$L21,"") | N21: =IF(AND($J21="Текущие",OR(Главная!$F$6="Все",$B21=Главная!$F$6),OR(Главная!$F$7="Все",$C21=Главная!$F$7)),$L21,"") | O21: =IF(AND($J21="Плановые",OR(Главная!$F$6="Все",$B21=Главная!$F$6),OR(Главная!$F$7="Все",$C21=Главная!$F$7)),$L21,"") | P21: =IF(J21="Выполнено",ROW(),"") -> 21
A22: Задача РОПу списов сотрудников графиков отправить | B22: Оптовка | C22: Высокий | D22: Выполнено | F22: 46301 | G22: Разово | H22: 30 мин | J22: =IF(TRIM(A22)="","",IF(D22="Выполнено","Выполнено",IF(OR(C22="Срочно",AND(F22<>"",F22<=TODAY())),"Срочные",IF(OR(D22="Отложено",C22="Низкий",AND(F22<>"",F22>TODAY()+Справочники!$H$2)),"Плановые","Текущие")))) -> Выполнено | K22: =IF(OR(A22="",D22="Выполнено"),"",IF(F22="",IF(AND(G22<>"",G22<>"Разово"),"↻ "&G22,""),IF(F22<TODAY(),"Просрочено на "&(TODAY()-F22)&" дн.",IF(F22=TODAY(),"Сегодня",IF(F22=TODAY()+1,"Завтра","Через "&(F22-TODAY())&" дн."))))) | L22: =IF(J22="","",(IF(AND(F22<>"",F22<TODAY()),0,1)*10000000+IFERROR(MATCH(C22,{"Срочно","Высокий","Средний","Низкий"},0),5)*100000+IF(F22="",99999,F22))*1000+ROW()) -> 10246301022 | M22: =IF(AND($J22="Срочные",OR(Главная!$F$6="Все",$B22=Главная!$F$6),OR(Главная!$F$7="Все",$C22=Главная!$F$7)),$L22,"") | N22: =IF(AND($J22="Текущие",OR(Главная!$F$6="Все",$B22=Главная!$F$6),OR(Главная!$F$7="Все",$C22=Главная!$F$7)),$L22,"") | O22: =IF(AND($J22="Плановые",OR(Главная!$F$6="Все",$B22=Главная!$F$6),OR(Главная!$F$7="Все",$C22=Главная!$F$7)),$L22,"") | P22: =IF(J22="Выполнено",ROW(),"") -> 22
A23: Телефония взять в контроль,оплата через Гульжайны | B23: Оптовка | C23: Срочно | D23: Выполнено | F23: 46302 | G23: Разово | H23: 15 мин | J23: =IF(TRIM(A23)="","",IF(D23="Выполнено","Выполнено",IF(OR(C23="Срочно",AND(F23<>"",F23<=TODAY())),"Срочные",IF(OR(D23="Отложено",C23="Низкий",AND(F23<>"",F23>TODAY()+Справочники!$H$2)),"Плановые","Текущие")))) -> Выполнено | K23: =IF(OR(A23="",D23="Выполнено"),"",IF(F23="",IF(AND(G23<>"",G23<>"Разово"),"↻ "&G23,""),IF(F23<TODAY(),"Просрочено на "&(TODAY()-F23)&" дн.",IF(F23=TODAY(),"Сегодня",IF(F23=TODAY()+1,"Завтра","Через "&(F23-TODAY())&" дн."))))) | L23: =IF(J23="","",(IF(AND(F23<>"",F23<TODAY()),0,1)*10000000+IFERROR(MATCH(C23,{"Срочно","Высокий","Средний","Низкий"},0),5)*100000+IF(F23="",99999,F23))*1000+ROW()) -> 10146302023 | M23: =IF(AND($J23="Срочные",OR(Главная!$F$6="Все",$B23=Главная!$F$6),OR(Главная!$F$7="Все",$C23=Главная!$F$7)),$L23,"") | N23: =IF(AND($J23="Текущие",OR(Главная!$F$6="Все",$B23=Главная!$F$6),OR(Главная!$F$7="Все",$C23=Главная!$F$7)),$L23,"") | O23: =IF(AND($J23="Плановые",OR(Главная!$F$6="Все",$B23=Главная!$F$6),OR(Главная!$F$7="Все",$C23=Главная!$F$7)),$L23,"") | P23: =IF(J23="Выполнено",ROW(),"") -> 23
A24: Договор о неразглашений конф информации, подписать всех сотрудников | B24: Управление | C24: Высокий | D24: В работе | F24: 46302 | G24: Разово | H24: 15 мин | I24: отделам отправила весь регламент жду пописи | J24: =IF(TRIM(A24)="","",IF(D24="Выполнено","Выполнено",IF(OR(C24="Срочно",AND(F24<>"",F24<=TODAY())),"Срочные",IF(OR(D24="Отложено",C24="Низкий",AND(F24<>"",F24>TODAY()+Справочники!$H$2)),"Плановые","Текущие")))) -> Текущие | K24: =IF(OR(A24="",D24="Выполнено"),"",IF(F24="",IF(AND(G24<>"",G24<>"Разово"),"↻ "&G24,""),IF(F24<TODAY(),"Просрочено на "&(TODAY()-F24)&" дн.",IF(F24=TODAY(),"Сегодня",IF(F24=TODAY()+1,"Завтра","Через "&(F24-TODAY())&" дн."))))) -> Завтра | L24: =IF(J24="","",(IF(AND(F24<>"",F24<TODAY()),0,1)*10000000+IFERROR(MATCH(C24,{"Срочно","Высокий","Средний","Низкий"},0),5)*100000+IF(F24="",99999,F24))*1000+ROW()) -> 10246302024 | M24: =IF(AND($J24="Срочные",OR(Главная!$F$6="Все",$B24=Главная!$F$6),OR(Главная!$F$7="Все",$C24=Главная!$F$7)),$L24,"") | N24: =IF(AND($J24="Текущие",OR(Главная!$F$6="Все",$B24=Главная!$F$6),OR(Главная!$F$7="Все",$C24=Главная!$F$7)),$L24,"") -> 10246302024 | O24: =IF(AND($J24="Плановые",OR(Главная!$F$6="Все",$B24=Главная!$F$6),OR(Главная!$F$7="Все",$C24=Главная!$F$7)),$L24,"") | P24: =IF(J24="Выполнено",ROW(),"")
A25: вторник пятница в область машины отгрузки не ездят в Основном все фуры по регионам стоят | B25: Оптовка | D25: Не начато | G25: Разово | J25: =IF(TRIM(A25)="","",IF(D25="Выполнено","Выполнено",IF(OR(C25="Срочно",AND(F25<>"",F25<=TODAY())),"Срочные",IF(OR(D25="Отложено",C25="Низкий",AND(F25<>"",F25>TODAY()+Справочники!$H$2)),"Плановые","Текущие")))) -> Текущие | K25: =IF(OR(A25="",D25="Выполнено"),"",IF(F25="",IF(AND(G25<>"",G25<>"Разово"),"↻ "&G25,""),IF(F25<TODAY(),"Просрочено на "&(TODAY()-F25)&" дн.",IF(F25=TODAY(),"Сегодня",IF(F25=TODAY()+1,"Завтра","Через "&(F25-TODAY())&" дн."))))) | L25: =IF(J25="","",(IF(AND(F25<>"",F25<TODAY()),0,1)*10000000+IFERROR(MATCH(C25,{"Срочно","Высокий","Средний","Низкий"},0),5)*100000+IF(F25="",99999,F25))*1000+ROW()) -> 10599999025 | M25: =IF(AND($J25="Срочные",OR(Главная!$F$6="Все",$B25=Главная!$F$6),OR(Главная!$F$7="Все",$C25=Главная!$F$7)),$L25,"") | N25: =IF(AND($J25="Текущие",OR(Главная!$F$6="Все",$B25=Главная!$F$6),OR(Главная!$F$7="Все",$C25=Главная!$F$7)),$L25,"") -> 10599999025 | O25: =IF(AND($J25="Плановые",OR(Главная!$F$6="Все",$B25=Главная!$F$6),OR(Главная!$F$7="Все",$C25=Главная!$F$7)),$L25,"") | P25: =IF(J25="Выполнено",ROW(),"")
A26: Продать машины грузовые, обновить все машины,машину по под 0 процентов, от3 до5 лизинг | B26: Управление | C26: Средний | D26: В работе | G26: Ежедневно | H26: 30 мин | I26: от 5 до 10 млн, 5 тонник груз подьем 6-8 тонн | J26: =IF(TRIM(A26)="","",IF(D26="Выполнено","Выполнено",IF(OR(C26="Срочно",AND(F26<>"",F26<=TODAY())),"Срочные",IF(OR(D26="Отложено",C26="Низкий",AND(F26<>"",F26>TODAY()+Справочники!$H$2)),"Плановые","Текущие")))) -> Текущие | K26: =IF(OR(A26="",D26="Выполнено"),"",IF(F26="",IF(AND(G26<>"",G26<>"Разово"),"↻ "&G26,""),IF(F26<TODAY(),"Просрочено на "&(TODAY()-F26)&" дн.",IF(F26=TODAY(),"Сегодня",IF(F26=TODAY()+1,"Завтра","Через "&(F26-TODAY())&" дн."))))) -> ↻ Ежедневно | L26: =IF(J26="","",(IF(AND(F26<>"",F26<TODAY()),0,1)*10000000+IFERROR(MATCH(C26,{"Срочно","Высокий","Средний","Низкий"},0),5)*100000+IF(F26="",99999,F26))*1000+ROW()) -> 10399999026 | M26: =IF(AND($J26="Срочные",OR(Главная!$F$6="Все",$B26=Главная!$F$6),OR(Главная!$F$7="Все",$C26=Главная!$F$7)),$L26,"") | N26: =IF(AND($J26="Текущие",OR(Главная!$F$6="Все",$B26=Главная!$F$6),OR(Главная!$F$7="Все",$C26=Главная!$F$7)),$L26,"") -> 10399999026 | O26: =IF(AND($J26="Плановые",OR(Главная!$F$6="Все",$B26=Главная!$F$6),OR(Главная!$F$7="Все",$C26=Главная!$F$7)),$L26,"") | P26: =IF(J26="Выполнено",ROW(),"")
A27: Светофор магазин, по ним ждем Ханни | B27: Подгузники / маркетинг | C27: Средний | D27: Отложено | G27: Разово | H27: 1 час | J27: =IF(TRIM(A27)="","",IF(D27="Выполнено","Выполнено",IF(OR(C27="Срочно",AND(F27<>"",F27<=TODAY())),"Срочные",IF(OR(D27="Отложено",C27="Низкий",AND(F27<>"",F27>TODAY()+Справочники!$H$2)),"Плановые","Текущие")))) -> Плановые | K27: =IF(OR(A27="",D27="Выполнено"),"",IF(F27="",IF(AND(G27<>"",G27<>"Разово"),"↻ "&G27,""),IF(F27<TODAY(),"Просрочено на "&(TODAY()-F27)&" дн.",IF(F27=TODAY(),"Сегодня",IF(F27=TODAY()+1,"Завтра","Через "&(F27-TODAY())&" дн."))))) | L27: =IF(J27="","",(IF(AND(F27<>"",F27<TODAY()),0,1)*10000000+IFERROR(MATCH(C27,{"Срочно","Высокий","Средний","Низкий"},0),5)*100000+IF(F27="",99999,F27))*1000+ROW()) -> 10399999027 | M27: =IF(AND($J27="Срочные",OR(Главная!$F$6="Все",$B27=Главная!$F$6),OR(Главная!$F$7="Все",$C27=Главная!$F$7)),$L27,"") | N27: =IF(AND($J27="Текущие",OR(Главная!$F$6="Все",$B27=Главная!$F$6),OR(Главная!$F$7="Все",$C27=Главная!$F$7)),$L27,"") | O27: =IF(AND($J27="Плановые",OR(Главная!$F$6="Все",$B27=Главная!$F$6),OR(Главная!$F$7="Все",$C27=Главная!$F$7)),$L27,"") -> 10399999027 | P27: =IF(J27="Выполнено",ROW(),"")
A28: миграционные вопросы решить по трудоустройстве | B28: Управление | C28: Высокий | D28: Отложено | G28: Разово | J28: =IF(TRIM(A28)="","",IF(D28="Выполнено","Выполнено",IF(OR(C28="Срочно",AND(F28<>"",F28<=TODAY())),"Срочные",IF(OR(D28="Отложено",C28="Низкий",AND(F28<>"",F28>TODAY()+Справочники!$H$2)),"Плановые","Текущие")))) -> Плановые | K28: =IF(OR(A28="",D28="Выполнено"),"",IF(F28="",IF(AND(G28<>"",G28<>"Разово"),"↻ "&G28,""),IF(F28<TODAY(),"Просрочено на "&(TODAY()-F28)&" дн.",IF(F28=TODAY(),"Сегодня",IF(F28=TODAY()+1,"Завтра","Через "&(F28-TODAY())&" дн."))))) | L28: =IF(J28="","",(IF(AND(F28<>"",F28<TODAY()),0,1)*10000000+IFERROR(MATCH(C28,{"Срочно","Высокий","Средний","Низкий"},0),5)*100000+IF(F28="",99999,F28))*1000+ROW()) -> 10299999028 | M28: =IF(AND($J28="Срочные",OR(Главная!$F$6="Все",$B28=Главная!$F$6),OR(Главная!$F$7="Все",$C28=Главная!$F$7)),$L28,"") | N28: =IF(AND($J28="Текущие",OR(Главная!$F$6="Все",$B28=Главная!$F$6),OR(Главная!$F$7="Все",$C28=Главная!$F$7)),$L28,"") | O28: =IF(AND($J28="Плановые",OR(Главная!$F$6="Все",$B28=Главная!$F$6),OR(Главная!$F$7="Все",$C28=Главная!$F$7)),$L28,"") -> 10299999028 | P28: =IF(J28="Выполнено",ROW(),"")
A29: стационарные огнетушетели на колесах 4 шт купитьи потсавить | B29: Оптовка | D29: Не начато | G29: Разово | J29: =IF(TRIM(A29)="","",IF(D29="Выполнено","Выполнено",IF(OR(C29="Срочно",AND(F29<>"",F29<=TODAY())),"Срочные",IF(OR(D29="Отложено",C29="Низкий",AND(F29<>"",F29>TODAY()+Справочники!$H$2)),"Плановые","Текущие")))) -> Текущие | K29: =IF(OR(A29="",D29="Выполнено"),"",IF(F29="",IF(AND(G29<>"",G29<>"Разово"),"↻ "&G29,""),IF(F29<TODAY(),"Просрочено на "&(TODAY()-F29)&" дн.",IF(F29=TODAY(),"Сегодня",IF(F29=TODAY()+1,"Завтра","Через "&(F29-TODAY())&" дн."))))) | L29: =IF(J29="","",(IF(AND(F29<>"",F29<TODAY()),0,1)*10000000+IFERROR(MATCH(C29,{"Срочно","Высокий","Средний","Низкий"},0),5)*100000+IF(F29="",99999,F29))*1000+ROW()) -> 10599999029 | M29: =IF(AND($J29="Срочные",OR(Главная!$F$6="Все",$B29=Главная!$F$6),OR(Главная!$F$7="Все",$C29=Главная!$F$7)),$L29,"") | N29: =IF(AND($J29="Текущие",OR(Главная!$F$6="Все",$B29=Главная!$F$6),OR(Главная!$F$7="Все",$C29=Главная!$F$7)),$L29,"") -> 10599999029 | O29: =IF(AND($J29="Плановые",OR(Главная!$F$6="Все",$B29=Главная!$F$6),OR(Главная!$F$7="Все",$C29=Главная!$F$7)),$L29,"") | P29: =IF(J29="Выполнено",ROW(),"")
A30: узнать у Улжан менеджера выход на Райымбек | B30: Оптовка | D30: Не начато | G30: Разово | J30: =IF(TRIM(A30)="","",IF(D30="Выполнено","Выполнено",IF(OR(C30="Срочно",AND(F30<>"",F30<=TODAY())),"Срочные",IF(OR(D30="Отложено",C30="Низкий",AND(F30<>"",F30>TODAY()+Справочники!$H$2)),"Плановые","Текущие")))) -> Текущие | K30: =IF(OR(A30="",D30="Выполнено"),"",IF(F30="",IF(AND(G30<>"",G30<>"Разово"),"↻ "&G30,""),IF(F30<TODAY(),"Просрочено на "&(TODAY()-F30)&" дн.",IF(F30=TODAY(),"Сегодня",IF(F30=TODAY()+1,"Завтра","Через "&(F30-TODAY())&" дн."))))) | L30: =IF(J30="","",(IF(AND(F30<>"",F30<TODAY()),0,1)*10000000+IFERROR(MATCH(C30,{"Срочно","Высокий","Средний","Низкий"},0),5)*100000+IF(F30="",99999,F30))*1000+ROW()) -> 10599999030 | M30: =IF(AND($J30="Срочные",OR(Главная!$F$6="Все",$B30=Главная!$F$6),OR(Главная!$F$7="Все",$C30=Главная!$F$7)),$L30,"") | N30: =IF(AND($J30="Текущие",OR(Главная!$F$6="Все",$B30=Главная!$F$6),OR(Главная!$F$7="Все",$C30=Главная!$F$7)),$L30,"") -> 10599999030 | O30: =IF(AND($J30="Плановые",OR(Главная!$F$6="Все",$B30=Главная!$F$6),OR(Главная!$F$7="Все",$C30=Главная!$F$7)),$L30,"") | P30: =IF(J30="Выполнено",ROW(),"")
A31: продать кофе машину | B31: Управление | D31: Не начато | G31: Разово | J31: =IF(TRIM(A31)="","",IF(D31="Выполнено","Выполнено",IF(OR(C31="Срочно",AND(F31<>"",F31<=TODAY())),"Срочные",IF(OR(D31="Отложено",C31="Низкий",AND(F31<>"",F31>TODAY()+Справочники!$H$2)),"Плановые","Текущие")))) -> Текущие | K31: =IF(OR(A31="",D31="Выполнено"),"",IF(F31="",IF(AND(G31<>"",G31<>"Разово"),"↻ "&G31,""),IF(F31<TODAY(),"Просрочено на "&(TODAY()-F31)&" дн.",IF(F31=TODAY(),"Сегодня",IF(F31=TODAY()+1,"Завтра","Через "&(F31-TODAY())&" дн."))))) | L31: =IF(J31="","",(IF(AND(F31<>"",F31<TODAY()),0,1)*10000000+IFERROR(MATCH(C31,{"Срочно","Высокий","Средний","Низкий"},0),5)*100000+IF(F31="",99999,F31))*1000+ROW()) -> 10599999031 | M31: =IF(AND($J31="Срочные",OR(Главная!$F$6="Все",$B31=Главная!$F$6),OR(Главная!$F$7="Все",$C31=Главная!$F$7)),$L31,"") | N31: =IF(AND($J31="Текущие",OR(Главная!$F$6="Все",$B31=Главная!$F$6),OR(Главная!$F$7="Все",$C31=Главная!$F$7)),$L31,"") -> 10599999031 | O31: =IF(AND($J31="Плановые",OR(Главная!$F$6="Все",$B31=Главная!$F$6),OR(Главная!$F$7="Все",$C31=Главная!$F$7)),$L31,"") | P31: =IF(J31="Выполнено",ROW(),"")
A32: водитель экспедитор и торговый | B32: Найм | D32: Не начато | G32: Разово | J32: =IF(TRIM(A32)="","",IF(D32="Выполнено","Выполнено",IF(OR(C32="Срочно",AND(F32<>"",F32<=TODAY())),"Срочные",IF(OR(D32="Отложено",C32="Низкий",AND(F32<>"",F32>TODAY()+Справочники!$H$2)),"Плановые","Текущие")))) -> Текущие | K32: =IF(OR(A32="",D32="Выполнено"),"",IF(F32="",IF(AND(G32<>"",G32<>"Разово"),"↻ "&G32,""),IF(F32<TODAY(),"Просрочено на "&(TODAY()-F32)&" дн.",IF(F32=TODAY(),"Сегодня",IF(F32=TODAY()+1,"Завтра","Через "&(F32-TODAY())&" дн."))))) | L32: =IF(J32="","",(IF(AND(F32<>"",F32<TODAY()),0,1)*10000000+IFERROR(MATCH(C32,{"Срочно","Высокий","Средний","Низкий"},0),5)*100000+IF(F32="",99999,F32))*1000+ROW()) -> 10599999032 | M32: =IF(AND($J32="Срочные",OR(Главная!$F$6="Все",$B32=Главная!$F$6),OR(Главная!$F$7="Все",$C32=Главная!$F$7)),$L32,"") | N32: =IF(AND($J32="Текущие",OR(Главная!$F$6="Все",$B32=Главная!$F$6),OR(Главная!$F$7="Все",$C32=Главная!$F$7)),$L32,"") -> 10599999032 | O32: =IF(AND($J32="Плановые",OR(Главная!$F$6="Все",$B32=Главная!$F$6),OR(Главная!$F$7="Все",$C32=Главная!$F$7)),$L32,"") | P32: =IF(J32="Выполнено",ROW(),"")
A33: журнал безопасности заполнить | B33: Оптовка | D33: Не начато | G33: Разово | J33: =IF(TRIM(A33)="","",IF(D33="Выполнено","Выполнено",IF(OR(C33="Срочно",AND(F33<>"",F33<=TODAY())),"Срочные",IF(OR(D33="Отложено",C33="Низкий",AND(F33<>"",F33>TODAY()+Справочники!$H$2)),"Плановые","Текущие")))) -> Текущие | K33: =IF(OR(A33="",D33="Выполнено"),"",IF(F33="",IF(AND(G33<>"",G33<>"Разово"),"↻ "&G33,""),IF(F33<TODAY(),"Просрочено на "&(TODAY()-F33)&" дн.",IF(F33=TODAY(),"Сегодня",IF(F33=TODAY()+1,"Завтра","Через "&(F33-TODAY())&" дн."))))) | L33: =IF(J33="","",(IF(AND(F33<>"",F33<TODAY()),0,1)*10000000+IFERROR(MATCH(C33,{"Срочно","Высокий","Средний","Низкий"},0),5)*100000+IF(F33="",99999,F33))*1000+ROW()) -> 10599999033 | M33: =IF(AND($J33="Срочные",OR(Главная!$F$6="Все",$B33=Главная!$F$6),OR(Главная!$F$7="Все",$C33=Главная!$F$7)),$L33,"") | N33: =IF(AND($J33="Текущие",OR(Главная!$F$6="Все",$B33=Главная!$F$6),OR(Главная!$F$7="Все",$C33=Главная!$F$7)),$L33,"") -> 10599999033 | O33: =IF(AND($J33="Плановые",OR(Главная!$F$6="Все",$B33=Главная!$F$6),OR(Главная!$F$7="Все",$C33=Главная!$F$7)),$L33,"") | P33: =IF(J33="Выполнено",ROW(),"")
A34: досконально отработать по пожаоной безопасности на чьей это ответсенности арендатор или арендодатель,говый договор запросить | B34: Оптовка | D34: Не начато | G34: Разово | J34: =IF(TRIM(A34)="","",IF(D34="Выполнено","Выполнено",IF(OR(C34="Срочно",AND(F34<>"",F34<=TODAY())),"Срочные",IF(OR(D34="Отложено",C34="Низкий",AND(F34<>"",F34>TODAY()+Справочники!$H$2)),"Плановые","Текущие")))) -> Текущие | K34: =IF(OR(A34="",D34="Выполнено"),"",IF(F34="",IF(AND(G34<>"",G34<>"Разово"),"↻ "&G34,""),IF(F34<TODAY(),"Просрочено на "&(TODAY()-F34)&" дн.",IF(F34=TODAY(),"Сегодня",IF(F34=TODAY()+1,"Завтра","Через "&(F34-TODAY())&" дн."))))) | L34: =IF(J34="","",(IF(AND(F34<>"",F34<TODAY()),0,1)*10000000+IFERROR(MATCH(C34,{"Срочно","Высокий","Средний","Низкий"},0),5)*100000+IF(F34="",99999,F34))*1000+ROW()) -> 10599999034 | M34: =IF(AND($J34="Срочные",OR(Главная!$F$6="Все",$B34=Главная!$F$6),OR(Главная!$F$7="Все",$C34=Главная!$F$7)),$L34,"") | N34: =IF(AND($J34="Текущие",OR(Главная!$F$6="Все",$B34=Главная!$F$6),OR(Главная!$F$7="Все",$C34=Главная!$F$7)),$L34,"") -> 10599999034 | O34: =IF(AND($J34="Плановые",OR(Главная!$F$6="Все",$B34=Главная!$F$6),OR(Главная!$F$7="Все",$C34=Главная!$F$7)),$L34,"") | P34: =IF(J34="Выполнено",ROW(),"")
A35: Орг структуру добить переделать | B35: Управление | D35: Не начато | G35: Разово | J35: =IF(TRIM(A35)="","",IF(D35="Выполнено","Выполнено",IF(OR(C35="Срочно",AND(F35<>"",F35<=TODAY())),"Срочные",IF(OR(D35="Отложено",C35="Низкий",AND(F35<>"",F35>TODAY()+Справочники!$H$2)),"Плановые","Текущие")))) -> Текущие | K35: =IF(OR(A35="",D35="Выполнено"),"",IF(F35="",IF(AND(G35<>"",G35<>"Разово"),"↻ "&G35,""),IF(F35<TODAY(),"Просрочено на "&(TODAY()-F35)&" дн.",IF(F35=TODAY(),"Сегодня",IF(F35=TODAY()+1,"Завтра","Через "&(F35-TODAY())&" дн."))))) | L35: =IF(J35="","",(IF(AND(F35<>"",F35<TODAY()),0,1)*10000000+IFERROR(MATCH(C35,{"Срочно","Высокий","Средний","Низкий"},0),5)*100000+IF(F35="",99999,F35))*1000+ROW()) -> 10599999035 | M35: =IF(AND($J35="Срочные",OR(Главная!$F$6="Все",$B35=Главная!$F$6),OR(Главная!$F$7="Все",$C35=Главная!$F$7)),$L35,"") | N35: =IF(AND($J35="Текущие",OR(Главная!$F$6="Все",$B35=Главная!$F$6),OR(Главная!$F$7="Все",$C35=Главная!$F$7)),$L35,"") -> 10599999035 | O35: =IF(AND($J35="Плановые",OR(Главная!$F$6="Все",$B35=Главная!$F$6),OR(Главная!$F$7="Все",$C35=Главная!$F$7)),$L35,"") | P35: =IF(J35="Выполнено",ROW(),"")
A36: съездить на осмотр машины и на обшежитие завтра | D36: Не начато | G36: Разово | J36: =IF(TRIM(A36)="","",IF(D36="Выполнено","Выполнено",IF(OR(C36="Срочно",AND(F36<>"",F36<=TODAY())),"Срочные",IF(OR(D36="Отложено",C36="Низкий",AND(F36<>"",F36>TODAY()+Справочники!$H$2)),"Плановые","Текущие")))) -> Текущие | K36: =IF(OR(A36="",D36="Выполнено"),"",IF(F36="",IF(AND(G36<>"",G36<>"Разово"),"↻ "&G36,""),IF(F36<TODAY(),"Просрочено на "&(TODAY()-F36)&" дн.",IF(F36=TODAY(),"Сегодня",IF(F36=TODAY()+1,"Завтра","Через "&(F36-TODAY())&" дн."))))) | L36: =IF(J36="","",(IF(AND(F36<>"",F36<TODAY()),0,1)*10000000+IFERROR(MATCH(C36,{"Срочно","Высокий","Средний","Низкий"},0),5)*100000+IF(F36="",99999,F36))*1000+ROW()) -> 10599999036 | M36: =IF(AND($J36="Срочные",OR(Главная!$F$6="Все",$B36=Главная!$F$6),OR(Главная!$F$7="Все",$C36=Главная!$F$7)),$L36,"") | N36: =IF(AND($J36="Текущие",OR(Главная!$F$6="Все",$B36=Главная!$F$6),OR(Главная!$F$7="Все",$C36=Главная!$F$7)),$L36,"") -> 10599999036 | O36: =IF(AND($J36="Плановые",OR(Главная!$F$6="Все",$B36=Главная!$F$6),OR(Главная!$F$7="Все",$C36=Главная!$F$7)),$L36,"") | P36: =IF(J36="Выполнено",ROW(),"")
A37: короткий отчет сделать исходя от документов, контроль бухгалтерий на аутсорсе | B37: Управление | D37: Не начато | G37: Разово | J37: =IF(TRIM(A37)="","",IF(D37="Выполнено","Выполнено",IF(OR(C37="Срочно",AND(F37<>"",F37<=TODAY())),"Срочные",IF(OR(D37="Отложено",C37="Низкий",AND(F37<>"",F37>TODAY()+Справочники!$H$2)),"Плановые","Текущие")))) -> Текущие | K37: =IF(OR(A37="",D37="Выполнено"),"",IF(F37="",IF(AND(G37<>"",G37<>"Разово"),"↻ "&G37,""),IF(F37<TODAY(),"Просрочено на "&(TODAY()-F37)&" дн.",IF(F37=TODAY(),"Сегодня",IF(F37=TODAY()+1,"Завтра","Через "&(F37-TODAY())&" дн."))))) | L37: =IF(J37="","",(IF(AND(F37<>"",F37<TODAY()),0,1)*10000000+IFERROR(MATCH(C37,{"Срочно","Высокий","Средний","Низкий"},0),5)*100000+IF(F37="",99999,F37))*1000+ROW()) -> 10599999037 | M37: =IF(AND($J37="Срочные",OR(Главная!$F$6="Все",$B37=Главная!$F$6),OR(Главная!$F$7="Все",$C37=Главная!$F$7)),$L37,"") | N37: =IF(AND($J37="Текущие",OR(Главная!$F$6="Все",$B37=Главная!$F$6),OR(Главная!$F$7="Все",$C37=Главная!$F$7)),$L37,"") -> 10599999037 | O37: =IF(AND($J37="Плановые",OR(Главная!$F$6="Все",$B37=Главная!$F$6),OR(Главная!$F$7="Все",$C37=Главная!$F$7)),$L37,"") | P37: =IF(J37="Выполнено",ROW(),"")
A38: разработать Кипиай исходя из возможности компании, склад, экспед | B38: Управление | D38: Не начато | G38: Разово | J38: =IF(TRIM(A38)="","",IF(D38="Выполнено","Выполнено",IF(OR(C38="Срочно",AND(F38<>"",F38<=TODAY())),"Срочные",IF(OR(D38="Отложено",C38="Низкий",AND(F38<>"",F38>TODAY()+Справочники!$H$2)),"Плановые","Текущие")))) -> Текущие | K38: =IF(OR(A38="",D38="Выполнено"),"",IF(F38="",IF(AND(G38<>"",G38<>"Разово"),"↻ "&G38,""),IF(F38<TODAY(),"Просрочено на "&(TODAY()-F38)&" дн.",IF(F38=TODAY(),"Сегодня",IF(F38=TODAY()+1,"Завтра","Через "&(F38-TODAY())&" дн."))))) | L38: =IF(J38="","",(IF(AND(F38<>"",F38<TODAY()),0,1)*10000000+IFERROR(MATCH(C38,{"Срочно","Высокий","Средний","Низкий"},0),5)*100000+IF(F38="",99999,F38))*1000+ROW()) -> 10599999038 | M38: =IF(AND($J38="Срочные",OR(Главная!$F$6="Все",$B38=Главная!$F$6),OR(Главная!$F$7="Все",$C38=Главная!$F$7)),$L38,"") | N38: =IF(AND($J38="Текущие",OR(Главная!$F$6="Все",$B38=Главная!$F$6),OR(Главная!$F$7="Все",$C38=Главная!$F$7)),$L38,"") -> 10599999038 | O38: =IF(AND($J38="Плановые",OR(Главная!$F$6="Все",$B38=Главная!$F$6),OR(Главная!$F$7="Все",$C38=Главная!$F$7)),$L38,"") | P38: =IF(J38="Выполнено",ROW(),"")
J39: =IF(TRIM(A39)="","",IF(D39="Выполнено","Выполнено",IF(OR(C39="Срочно",AND(F39<>"",F39<=TODAY())),"Срочные",IF(OR(D39="Отложено",C39="Низкий",AND(F39<>"",F39>TODAY()+Справочники!$H$2)),"Плановые","Текущие")))) | K39: =IF(OR(A39="",D39="Выполнено"),"",IF(F39="",IF(AND(G39<>"",G39<>"Разово"),"↻ "&G39,""),IF(F39<TODAY(),"Просрочено на "&(TODAY()-F39)&" дн.",IF(F39=TODAY(),"Сегодня",IF(F39=TODAY()+1,"Завтра","Через "&(F39-TODAY())&" дн."))))) | L39: =IF(J39="","",(IF(AND(F39<>"",F39<TODAY()),0,1)*10000000+IFERROR(MATCH(C39,{"Срочно","Высокий","Средний","Низкий"},0),5)*100000+IF(F39="",99999,F39))*1000+ROW()) | M39: =IF(AND($J39="Срочные",OR(Главная!$F$6="Все",$B39=Главная!$F$6),OR(Главная!$F$7="Все",$C39=Главная!$F$7)),$L39,"") | N39: =IF(AND($J39="Текущие",OR(Главная!$F$6="Все",$B39=Главная!$F$6),OR(Главная!$F$7="Все",$C39=Главная!$F$7)),$L39,"") | O39: =IF(AND($J39="Плановые",OR(Главная!$F$6="Все",$B39=Главная!$F$6),OR(Главная!$F$7="Все",$C39=Главная!$F$7)),$L39,"") | P39: =IF(J39="Выполнено",ROW(),"")
J40: =IF(TRIM(A40)="","",IF(D40="Выполнено","Выполнено",IF(OR(C40="Срочно",AND(F40<>"",F40<=TODAY())),"Срочные",IF(OR(D40="Отложено",C40="Низкий",AND(F40<>"",F40>TODAY()+Справочники!$H$2)),"Плановые","Текущие")))) | K40: =IF(OR(A40="",D40="Выполнено"),"",IF(F40="",IF(AND(G40<>"",G40<>"Разово"),"↻ "&G40,""),IF(F40<TODAY(),"Просрочено на "&(TODAY()-F40)&" дн.",IF(F40=TODAY(),"Сегодня",IF(F40=TODAY()+1,"Завтра","Через "&(F40-TODAY())&" дн."))))) | L40: =IF(J40="","",(IF(AND(F40<>"",F40<TODAY()),0,1)*10000000+IFERROR(MATCH(C40,{"Срочно","Высокий","Средний","Низкий"},0),5)*100000+IF(F40="",99999,F40))*1000+ROW()) | M40: =IF(AND($J40="Срочные",OR(Главная!$F$6="Все",$B40=Главная!$F$6),OR(Главная!$F$7="Все",$C40=Главная!$F$7)),$L40,"") | N40: =IF(AND($J40="Текущие",OR(Главная!$F$6="Все",$B40=Главная!$F$6),OR(Главная!$F$7="Все",$C40=Главная!$F$7)),$L40,"") | O40: =IF(AND($J40="Плановые",OR(Главная!$F$6="Все",$B40=Главная!$F$6),OR(Главная!$F$7="Все",$C40=Главная!$F$7)),$L40,"") | P40: =IF(J40="Выполнено",ROW(),"")
J41: =IF(TRIM(A41)="","",IF(D41="Выполнено","Выполнено",IF(OR(C41="Срочно",AND(F41<>"",F41<=TODAY())),"Срочные",IF(OR(D41="Отложено",C41="Низкий",AND(F41<>"",F41>TODAY()+Справочники!$H$2)),"Плановые","Текущие")))) | K41: =IF(OR(A41="",D41="Выполнено"),"",IF(F41="",IF(AND(G41<>"",G41<>"Разово"),"↻ "&G41,""),IF(F41<TODAY(),"Просрочено на "&(TODAY()-F41)&" дн.",IF(F41=TODAY(),"Сегодня",IF(F41=TODAY()+1,"Завтра","Через "&(F41-TODAY())&" дн."))))) | L41: =IF(J41="","",(IF(AND(F41<>"",F41<TODAY()),0,1)*10000000+IFERROR(MATCH(C41,{"Срочно","Высокий","Средний","Низкий"},0),5)*100000+IF(F41="",99999,F41))*1000+ROW()) | M41: =IF(AND($J41="Срочные",OR(Главная!$F$6="Все",$B41=Главная!$F$6),OR(Главная!$F$7="Все",$C41=Главная!$F$7)),$L41,"") | N41: =IF(AND($J41="Текущие",OR(Главная!$F$6="Все",$B41=Главная!$F$6),OR(Главная!$F$7="Все",$C41=Главная!$F$7)),$L41,"") | O41: =IF(AND($J41="Плановые",OR(Главная!$F$6="Все",$B41=Главная!$F$6),OR(Главная!$F$7="Все",$C41=Главная!$F$7)),$L41,"") | P41: =IF(J41="Выполнено",ROW(),"")
J42: =IF(TRIM(A42)="","",IF(D42="Выполнено","Выполнено",IF(OR(C42="Срочно",AND(F42<>"",F42<=TODAY())),"Срочные",IF(OR(D42="Отложено",C42="Низкий",AND(F42<>"",F42>TODAY()+Справочники!$H$2)),"Плановые","Текущие")))) | K42: =IF(OR(A42="",D42="Выполнено"),"",IF(F42="",IF(AND(G42<>"",G42<>"Разово"),"↻ "&G42,""),IF(F42<TODAY(),"Просрочено на "&(TODAY()-F42)&" дн.",IF(F42=TODAY(),"Сегодня",IF(F42=TODAY()+1,"Завтра","Через "&(F42-TODAY())&" дн."))))) | L42: =IF(J42="","",(IF(AND(F42<>"",F42<TODAY()),0,1)*10000000+IFERROR(MATCH(C42,{"Срочно","Высокий","Средний","Низкий"},0),5)*100000+IF(F42="",99999,F42))*1000+ROW()) | M42: =IF(AND($J42="Срочные",OR(Главная!$F$6="Все",$B42=Главная!$F$6),OR(Главная!$F$7="Все",$C42=Главная!$F$7)),$L42,"") | N42: =IF(AND($J42="Текущие",OR(Главная!$F$6="Все",$B42=Главная!$F$6),OR(Главная!$F$7="Все",$C42=Главная!$F$7)),$L42,"") | O42: =IF(AND($J42="Плановые",OR(Главная!$F$6="Все",$B42=Главная!$F$6),OR(Главная!$F$7="Все",$C42=Главная!$F$7)),$L42,"") | P42: =IF(J42="Выполнено",ROW(),"")
J43: =IF(TRIM(A43)="","",IF(D43="Выполнено","Выполнено",IF(OR(C43="Срочно",AND(F43<>"",F43<=TODAY())),"Срочные",IF(OR(D43="Отложено",C43="Низкий",AND(F43<>"",F43>TODAY()+Справочники!$H$2)),"Плановые","Текущие")))) | K43: =IF(OR(A43="",D43="Выполнено"),"",IF(F43="",IF(AND(G43<>"",G43<>"Разово"),"↻ "&G43,""),IF(F43<TODAY(),"Просрочено на "&(TODAY()-F43)&" дн.",IF(F43=TODAY(),"Сегодня",IF(F43=TODAY()+1,"Завтра","Через "&(F43-TODAY())&" дн."))))) | L43: =IF(J43="","",(IF(AND(F43<>"",F43<TODAY()),0,1)*10000000+IFERROR(MATCH(C43,{"Срочно","Высокий","Средний","Низкий"},0),5)*100000+IF(F43="",99999,F43))*1000+ROW()) | M43: =IF(AND($J43="Срочные",OR(Главная!$F$6="Все",$B43=Главная!$F$6),OR(Главная!$F$7="Все",$C43=Главная!$F$7)),$L43,"") | N43: =IF(AND($J43="Текущие",OR(Главная!$F$6="Все",$B43=Главная!$F$6),OR(Главная!$F$7="Все",$C43=Главная!$F$7)),$L43,"") | O43: =IF(AND($J43="Плановые",OR(Главная!$F$6="Все",$B43=Главная!$F$6),OR(Главная!$F$7="Все",$C43=Главная!$F$7)),$L43,"") | P43: =IF(J43="Выполнено",ROW(),"")
J44: =IF(TRIM(A44)="","",IF(D44="Выполнено","Выполнено",IF(OR(C44="Срочно",AND(F44<>"",F44<=TODAY())),"Срочные",IF(OR(D44="Отложено",C44="Низкий",AND(F44<>"",F44>TODAY()+Справочники!$H$2)),"Плановые","Текущие")))) | K44: =IF(OR(A44="",D44="Выполнено"),"",IF(F44="",IF(AND(G44<>"",G44<>"Разово"),"↻ "&G44,""),IF(F44<TODAY(),"Просрочено на "&(TODAY()-F44)&" дн.",IF(F44=TODAY(),"Сегодня",IF(F44=TODAY()+1,"Завтра","Через "&(F44-TODAY())&" дн."))))) | L44: =IF(J44="","",(IF(AND(F44<>"",F44<TODAY()),0,1)*10000000+IFERROR(MATCH(C44,{"Срочно","Высокий","Средний","Низкий"},0),5)*100000+IF(F44="",99999,F44))*1000+ROW()) | M44: =IF(AND($J44="Срочные",OR(Главная!$F$6="Все",$B44=Главная!$F$6),OR(Главная!$F$7="Все",$C44=Главная!$F$7)),$L44,"") | N44: =IF(AND($J44="Текущие",OR(Главная!$F$6="Все",$B44=Главная!$F$6),OR(Главная!$F$7="Все",$C44=Главная!$F$7)),$L44,"") | O44: =IF(AND($J44="Плановые",OR(Главная!$F$6="Все",$B44=Главная!$F$6),OR(Главная!$F$7="Все",$C44=Главная!$F$7)),$L44,"") | P44: =IF(J44="Выполнено",ROW(),"")
J45: =IF(TRIM(A45)="","",IF(D45="Выполнено","Выполнено",IF(OR(C45="Срочно",AND(F45<>"",F45<=TODAY())),"Срочные",IF(OR(D45="Отложено",C45="Низкий",AND(F45<>"",F45>TODAY()+Справочники!$H$2)),"Плановые","Текущие")))) | K45: =IF(OR(A45="",D45="Выполнено"),"",IF(F45="",IF(AND(G45<>"",G45<>"Разово"),"↻ "&G45,""),IF(F45<TODAY(),"Просрочено на "&(TODAY()-F45)&" дн.",IF(F45=TODAY(),"Сегодня",IF(F45=TODAY()+1,"Завтра","Через "&(F45-TODAY())&" дн."))))) | L45: =IF(J45="","",(IF(AND(F45<>"",F45<TODAY()),0,1)*10000000+IFERROR(MATCH(C45,{"Срочно","Высокий","Средний","Низкий"},0),5)*100000+IF(F45="",99999,F45))*1000+ROW()) | M45: =IF(AND($J45="Срочные",OR(Главная!$F$6="Все",$B45=Главная!$F$6),OR(Главная!$F$7="Все",$C45=Главная!$F$7)),$L45,"") | N45: =IF(AND($J45="Текущие",OR(Главная!$F$6="Все",$B45=Главная!$F$6),OR(Главная!$F$7="Все",$C45=Главная!$F$7)),$L45,"") | O45: =IF(AND($J45="Плановые",OR(Главная!$F$6="Все",$B45=Главная!$F$6),OR(Главная!$F$7="Все",$C45=Главная!$F$7)),$L45,"") | P45: =IF(J45="Выполнено",ROW(),"")
J46: =IF(TRIM(A46)="","",IF(D46="Выполнено","Выполнено",IF(OR(C46="Срочно",AND(F46<>"",F46<=TODAY())),"Срочные",IF(OR(D46="Отложено",C46="Низкий",AND(F46<>"",F46>TODAY()+Справочники!$H$2)),"Плановые","Текущие")))) | K46: =IF(OR(A46="",D46="Выполнено"),"",IF(F46="",IF(AND(G46<>"",G46<>"Разово"),"↻ "&G46,""),IF(F46<TODAY(),"Просрочено на "&(TODAY()-F46)&" дн.",IF(F46=TODAY(),"Сегодня",IF(F46=TODAY()+1,"Завтра","Через "&(F46-TODAY())&" дн."))))) | L46: =IF(J46="","",(IF(AND(F46<>"",F46<TODAY()),0,1)*10000000+IFERROR(MATCH(C46,{"Срочно","Высокий","Средний","Низкий"},0),5)*100000+IF(F46="",99999,F46))*1000+ROW()) | M46: =IF(AND($J46="Срочные",OR(Главная!$F$6="Все",$B46=Главная!$F$6),OR(Главная!$F$7="Все",$C46=Главная!$F$7)),$L46,"") | N46: =IF(AND($J46="Текущие",OR(Главная!$F$6="Все",$B46=Главная!$F$6),OR(Главная!$F$7="Все",$C46=Главная!$F$7)),$L46,"") | O46: =IF(AND($J46="Плановые",OR(Главная!$F$6="Все",$B46=Главная!$F$6),OR(Главная!$F$7="Все",$C46=Главная!$F$7)),$L46,"") | P46: =IF(J46="Выполнено",ROW(),"")
J47: =IF(TRIM(A47)="","",IF(D47="Выполнено","Выполнено",IF(OR(C47="Срочно",AND(F47<>"",F47<=TODAY())),"Срочные",IF(OR(D47="Отложено",C47="Низкий",AND(F47<>"",F47>TODAY()+Справочники!$H$2)),"Плановые","Текущие")))) | K47: =IF(OR(A47="",D47="Выполнено"),"",IF(F47="",IF(AND(G47<>"",G47<>"Разово"),"↻ "&G47,""),IF(F47<TODAY(),"Просрочено на "&(TODAY()-F47)&" дн.",IF(F47=TODAY(),"Сегодня",IF(F47=TODAY()+1,"Завтра","Через "&(F47-TODAY())&" дн."))))) | L47: =IF(J47="","",(IF(AND(F47<>"",F47<TODAY()),0,1)*10000000+IFERROR(MATCH(C47,{"Срочно","Высокий","Средний","Низкий"},0),5)*100000+IF(F47="",99999,F47))*1000+ROW()) | M47: =IF(AND($J47="Срочные",OR(Главная!$F$6="Все",$B47=Главная!$F$6),OR(Главная!$F$7="Все",$C47=Главная!$F$7)),$L47,"") | N47: =IF(AND($J47="Текущие",OR(Главная!$F$6="Все",$B47=Главная!$F$6),OR(Главная!$F$7="Все",$C47=Главная!$F$7)),$L47,"") | O47: =IF(AND($J47="Плановые",OR(Главная!$F$6="Все",$B47=Главная!$F$6),OR(Главная!$F$7="Все",$C47=Главная!$F$7)),$L47,"") | P47: =IF(J47="Выполнено",ROW(),"")
J48: =IF(TRIM(A48)="","",IF(D48="Выполнено","Выполнено",IF(OR(C48="Срочно",AND(F48<>"",F48<=TODAY())),"Срочные",IF(OR(D48="Отложено",C48="Низкий",AND(F48<>"",F48>TODAY()+Справочники!$H$2)),"Плановые","Текущие")))) | K48: =IF(OR(A48="",D48="Выполнено"),"",IF(F48="",IF(AND(G48<>"",G48<>"Разово"),"↻ "&G48,""),IF(F48<TODAY(),"Просрочено на "&(TODAY()-F48)&" дн.",IF(F48=TODAY(),"Сегодня",IF(F48=TODAY()+1,"Завтра","Через "&(F48-TODAY())&" дн."))))) | L48: =IF(J48="","",(IF(AND(F48<>"",F48<TODAY()),0,1)*10000000+IFERROR(MATCH(C48,{"Срочно","Высокий","Средний","Низкий"},0),5)*100000+IF(F48="",99999,F48))*1000+ROW()) | M48: =IF(AND($J48="Срочные",OR(Главная!$F$6="Все",$B48=Главная!$F$6),OR(Главная!$F$7="Все",$C48=Главная!$F$7)),$L48,"") | N48: =IF(AND($J48="Текущие",OR(Главная!$F$6="Все",$B48=Главная!$F$6),OR(Главная!$F$7="Все",$C48=Главная!$F$7)),$L48,"") | O48: =IF(AND($J48="Плановые",OR(Главная!$F$6="Все",$B48=Главная!$F$6),OR(Главная!$F$7="Все",$C48=Главная!$F$7)),$L48,"") | P48: =IF(J48="Выполнено",ROW(),"")
J49: =IF(TRIM(A49)="","",IF(D49="Выполнено","Выполнено",IF(OR(C49="Срочно",AND(F49<>"",F49<=TODAY())),"Срочные",IF(OR(D49="Отложено",C49="Низкий",AND(F49<>"",F49>TODAY()+Справочники!$H$2)),"Плановые","Текущие")))) | K49: =IF(OR(A49="",D49="Выполнено"),"",IF(F49="",IF(AND(G49<>"",G49<>"Разово"),"↻ "&G49,""),IF(F49<TODAY(),"Просрочено на "&(TODAY()-F49)&" дн.",IF(F49=TODAY(),"Сегодня",IF(F49=TODAY()+1,"Завтра","Через "&(F49-TODAY())&" дн."))))) | L49: =IF(J49="","",(IF(AND(F49<>"",F49<TODAY()),0,1)*10000000+IFERROR(MATCH(C49,{"Срочно","Высокий","Средний","Низкий"},0),5)*100000+IF(F49="",99999,F49))*1000+ROW()) | M49: =IF(AND($J49="Срочные",OR(Главная!$F$6="Все",$B49=Главная!$F$6),OR(Главная!$F$7="Все",$C49=Главная!$F$7)),$L49,"") | N49: =IF(AND($J49="Текущие",OR(Главная!$F$6="Все",$B49=Главная!$F$6),OR(Главная!$F$7="Все",$C49=Главная!$F$7)),$L49,"") | O49: =IF(AND($J49="Плановые",OR(Главная!$F$6="Все",$B49=Главная!$F$6),OR(Главная!$F$7="Все",$C49=Главная!$F$7)),$L49,"") | P49: =IF(J49="Выполнено",ROW(),"")
J50: =IF(TRIM(A50)="","",IF(D50="Выполнено","Выполнено",IF(OR(C50="Срочно",AND(F50<>"",F50<=TODAY())),"Срочные",IF(OR(D50="Отложено",C50="Низкий",AND(F50<>"",F50>TODAY()+Справочники!$H$2)),"Плановые","Текущие")))) | K50: =IF(OR(A50="",D50="Выполнено"),"",IF(F50="",IF(AND(G50<>"",G50<>"Разово"),"↻ "&G50,""),IF(F50<TODAY(),"Просрочено на "&(TODAY()-F50)&" дн.",IF(F50=TODAY(),"Сегодня",IF(F50=TODAY()+1,"Завтра","Через "&(F50-TODAY())&" дн."))))) | L50: =IF(J50="","",(IF(AND(F50<>"",F50<TODAY()),0,1)*10000000+IFERROR(MATCH(C50,{"Срочно","Высокий","Средний","Низкий"},0),5)*100000+IF(F50="",99999,F50))*1000+ROW()) | M50: =IF(AND($J50="Срочные",OR(Главная!$F$6="Все",$B50=Главная!$F$6),OR(Главная!$F$7="Все",$C50=Главная!$F$7)),$L50,"") | N50: =IF(AND($J50="Текущие",OR(Главная!$F$6="Все",$B50=Главная!$F$6),OR(Главная!$F$7="Все",$C50=Главная!$F$7)),$L50,"") | O50: =IF(AND($J50="Плановые",OR(Главная!$F$6="Все",$B50=Главная!$F$6),OR(Главная!$F$7="Все",$C50=Главная!$F$7)),$L50,"") | P50: =IF(J50="Выполнено",ROW(),"")
... J501: =IF(TRIM(A501)="","",IF(D501="Выполнено","Выполнено",IF(OR(C501="Срочно",AND(F501<>"",F501<=TODAY())),"Срочные",IF(OR(D501="Отложено",C501="Низкий",AND(F501<>"",F501>TODAY()+Справочники!$H$2)),"Плановые","Текущие")))) | K501: =IF(OR(A501="",D501="Выполнено"),"",IF(F501="",IF(AND(G501<>"",G501<>"Разово"),"↻ "&G501,""),IF(F501<TODAY(),"Просрочено на "&(TODAY()-F501)&" дн.",IF(F501=TODAY(),"Сегодня",IF(F501=TODAY()+1,"Завтра","Через "&(F501-TODAY())&" дн."))))) | L501: =IF(J501="","",(IF(AND(F501<>"",F501<TODAY()),0,1)*10000000+IFERROR(MATCH(C501,{"Срочно","Высокий","Средний","Низкий"},0),5)*100000+IF(F501="",99999,F501))*1000+ROW()) | M501: =IF(AND($J501="Срочные",OR(Главная!$F$6="Все",$B501=Главная!$F$6),OR(Главная!$F$7="Все",$C501=Главная!$F$7)),$L501,"") | N501: =IF(AND($J501="Текущие",OR(Главная!$F$6="Все",$B501=Главная!$F$6),OR(Главная!$F$7="Все",$C501=Главная!$F$7)),$L501,"") | O501: =IF(AND($J501="Плановые",OR(Главная!$F$6="Все",$B501=Главная!$F$6),OR(Главная!$F$7="Все",$C501=Главная!$F$7)),$L501,"") | P501: =IF(J501="Выполнено",ROW(),"")

Sheet Выполненные
A1: ВЫПОЛНЕННЫЕ ЗАДАЧИ
A2: ="Всего выполнено: "&COUNT(Задачи!$P$2:$P$501) -> Всего выполнено: 8
A3: Список заполняется автоматически, когда на листе «Задачи» ставится статус «Выполнено». Новые — сверху.
A4: № | B4: Задача | C4: Категория | D4: Приоритет | E4: Дата постановки | F4: Срок | G4: Комментарий / результат | H4: Стр.
A5: =IF($H5="","",ROWS(A$5:A5)) -> 1 | B5: =IF($H5="","",INDEX(Задачи!$A$1:$A$501,$H5)&"") -> Телефония взять в контроль,оплата через Гульжайны | C5: =IF($H5="","",INDEX(Задачи!$B$1:$B$501,$H5)&"") -> Оптовка | D5: =IF($H5="","",INDEX(Задачи!$C$1:$C$501,$H5)&"") -> Срочно | E5: =IF($H5="","",IF(INDEX(Задачи!$E$1:$E$501,$H5)="","",INDEX(Задачи!$E$1:$E$501,$H5))) | F5: =IF($H5="","",IF(INDEX(Задачи!$F$1:$F$501,$H5)="","",INDEX(Задачи!$F$1:$F$501,$H5))) -> 46302 | G5: =IF($H5="","",INDEX(Задачи!$I$1:$I$501,$H5)&"") | H5: =IFERROR(MOD(LARGE(Задачи!$P$2:$P$501,ROWS(H$5:H5)),1000),"") -> 23
A6: =IF($H6="","",ROWS(A$5:A6)) -> 2 | B6: =IF($H6="","",INDEX(Задачи!$A$1:$A$501,$H6)&"") -> Задача РОПу списов сотрудников графиков отправить | C6: =IF($H6="","",INDEX(Задачи!$B$1:$B$501,$H6)&"") -> Оптовка | D6: =IF($H6="","",INDEX(Задачи!$C$1:$C$501,$H6)&"") -> Высокий | E6: =IF($H6="","",IF(INDEX(Задачи!$E$1:$E$501,$H6)="","",INDEX(Задачи!$E$1:$E$501,$H6))) | F6: =IF($H6="","",IF(INDEX(Задачи!$F$1:$F$501,$H6)="","",INDEX(Задачи!$F$1:$F$501,$H6))) -> 46301 | G6: =IF($H6="","",INDEX(Задачи!$I$1:$I$501,$H6)&"") | H6: =IFERROR(MOD(LARGE(Задачи!$P$2:$P$501,ROWS(H$5:H6)),1000),"") -> 22
A7: =IF($H7="","",ROWS(A$5:A7)) -> 3 | B7: =IF($H7="","",INDEX(Задачи!$A$1:$A$501,$H7)&"") -> Решить вопрос по Алтел, сделать с компанией доп соглашение,купить тариф,заменить все старые номера | C7: =IF($H7="","",INDEX(Задачи!$B$1:$B$501,$H7)&"") -> Управление | D7: =IF($H7="","",INDEX(Задачи!$C$1:$C$501,$H7)&"") -> Срочно | E7: =IF($H7="","",IF(INDEX(Задачи!$E$1:$E$501,$H7)="","",INDEX(Задачи!$E$1:$E$501,$H7))) | F7: =IF($H7="","",IF(INDEX(Задачи!$F$1:$F$501,$H7)="","",INDEX(Задачи!$F$1:$F$501,$H7))) -> 46301 | G7: =IF($H7="","",INDEX(Задачи!$I$1:$I$501,$H7)&"") | H7: =IFERROR(MOD(LARGE(Задачи!$P$2:$P$501,ROWS(H$5:H7)),1000),"") -> 21
A8: =IF($H8="","",ROWS(A$5:A8)) -> 4 | B8: =IF($H8="","",INDEX(Задачи!$A$1:$A$501,$H8)&"") -> Страхование компаний ТМЦ, надо найти компании, от Гульзиры бух спросить анкету | C8: =IF($H8="","",INDEX(Задачи!$B$1:$B$501,$H8)&"") -> Управление | D8: =IF($H8="","",INDEX(Задачи!$C$1:$C$501,$H8)&"") -> Срочно | E8: =IF($H8="","",IF(INDEX(Задачи!$E$1:$E$501,$H8)="","",INDEX(Задачи!$E$1:$E$501,$H8))) | F8: =IF($H8="","",IF(INDEX(Задачи!$F$1:$F$501,$H8)="","",INDEX(Задачи!$F$1:$F$501,$H8))) -> 46302 | G8: =IF($H8="","",INDEX(Задачи!$I$1:$I$501,$H8)&"") -> приедут две компании на осмотр объекта сегодня Шеф: ждем ответ от Евразия Номад Аманат КП, до Халыка не дозвонилась | H8: =IFERROR(MOD(LARGE(Задачи!$P$2:$P$501,ROWS(H$5:H8)),1000),"") -> 17
A9: =IF($H9="","",ROWS(A$5:A9)) -> 5 | B9: =IF($H9="","",INDEX(Задачи!$A$1:$A$501,$H9)&"") -> Закончить мотивационную систему сотрудников | C9: =IF($H9="","",INDEX(Задачи!$B$1:$B$501,$H9)&"") -> Продажи / управление | D9: =IF($H9="","",INDEX(Задачи!$C$1:$C$501,$H9)&"") -> Срочно | E9: =IF($H9="","",IF(INDEX(Задачи!$E$1:$E$501,$H9)="","",INDEX(Задачи!$E$1:$E$501,$H9))) | F9: =IF($H9="","",IF(INDEX(Задачи!$F$1:$F$501,$H9)="","",INDEX(Задачи!$F$1:$F$501,$H9))) -> 46301 | G9: =IF($H9="","",INDEX(Задачи!$I$1:$I$501,$H9)&"") | H9: =IFERROR(MOD(LARGE(Задачи!$P$2:$P$501,ROWS(H$5:H9)),1000),"") -> 12
A10: =IF($H10="","",ROWS(A$5:A10)) -> 6 | B10: =IF($H10="","",INDEX(Задачи!$A$1:$A$501,$H10)&"") -> Поиск маркетолога | C10: =IF($H10="","",INDEX(Задачи!$B$1:$B$501,$H10)&"") -> Найм | D10: =IF($H10="","",INDEX(Задачи!$C$1:$C$501,$H10)&"") -> Высокий | E10: =IF($H10="","",IF(INDEX(Задачи!$E$1:$E$501,$H10)="","",INDEX(Задачи!$E$1:$E$501,$H10))) | F10: =IF($H10="","",IF(INDEX(Задачи!$F$1:$F$501,$H10)="","",INDEX(Задачи!$F$1:$F$501,$H10))) -> 46301 | G10: =IF($H10="","",INDEX(Задачи!$I$1:$I$501,$H10)&"") -> ждем ответа с 12 го октября выйдет на работу | H10: =IFERROR(MOD(LARGE(Задачи!$P$2:$P$501,ROWS(H$5:H10)),1000),"") -> 9
A11: =IF($H11="","",ROWS(A$5:A11)) -> 7 | B11: =IF($H11="","",INDEX(Задачи!$A$1:$A$501,$H11)&"") -> Разместить / обновить объявление на Krisha.kz по промбазе / по Таргету | C11: =IF($H11="","",INDEX(Задачи!$B$1:$B$501,$H11)&"") -> Промбаза | D11: =IF($H11="","",INDEX(Задачи!$C$1:$C$501,$H11)&"") -> Высокий | E11: =IF($H11="","",IF(INDEX(Задачи!$E$1:$E$501,$H11)="","",INDEX(Задачи!$E$1:$E$501,$H11))) | F11: =IF($H11="","",IF(INDEX(Задачи!$F$1:$F$501,$H11)="","",INDEX(Задачи!$F$1:$F$501,$H11))) -> 46301 | G11: =IF($H11="","",INDEX(Задачи!$I$1:$I$501,$H11)&"") | H11: =IFERROR(MOD(LARGE(Задачи!$P$2:$P$501,ROWS(H$5:H11)),1000),"") -> 3
A12: =IF($H12="","",ROWS(A$5:A12)) -> 8 | B12: =IF($H12="","",INDEX(Задачи!$A$1:$A$501,$H12)&"") -> Проверить и улучшить объявление промбазы на Krisha.kz | C12: =IF($H12="","",INDEX(Задачи!$B$1:$B$501,$H12)&"") -> Промбаза | D12: =IF($H12="","",INDEX(Задачи!$C$1:$C$501,$H12)&"") -> Высокий | E12: =IF($H12="","",IF(INDEX(Задачи!$E$1:$E$501,$H12)="","",INDEX(Задачи!$E$1:$E$501,$H12))) | F12: =IF($H12="","",IF(INDEX(Задачи!$F$1:$F$501,$H12)="","",INDEX(Задачи!$F$1:$F$501,$H12))) | G12: =IF($H12="","",INDEX(Задачи!$I$1:$I$501,$H12)&"") | H12: =IFERROR(MOD(LARGE(Задачи!$P$2:$P$501,ROWS(H$5:H12)),1000),"") -> 2
A13: =IF($H13="","",ROWS(A$5:A13)) | B13: =IF($H13="","",INDEX(Задачи!$A$1:$A$501,$H13)&"") | C13: =IF($H13="","",INDEX(Задачи!$B$1:$B$501,$H13)&"") | D13: =IF($H13="","",INDEX(Задачи!$C$1:$C$501,$H13)&"") | E13: =IF($H13="","",IF(INDEX(Задачи!$E$1:$E$501,$H13)="","",INDEX(Задачи!$E$1:$E$501,$H13))) | F13: =IF($H13="","",IF(INDEX(Задачи!$F$1:$F$501,$H13)="","",INDEX(Задачи!$F$1:$F$501,$H13))) | G13: =IF($H13="","",INDEX(Задачи!$I$1:$I$501,$H13)&"") | H13: =IFERROR(MOD(LARGE(Задачи!$P$2:$P$501,ROWS(H$5:H13)),1000),"")
A14: =IF($H14="","",ROWS(A$5:A14)) | B14: =IF($H14="","",INDEX(Задачи!$A$1:$A$501,$H14)&"") | C14: =IF($H14="","",INDEX(Задачи!$B$1:$B$501,$H14)&"") | D14: =IF($H14="","",INDEX(Задачи!$C$1:$C$501,$H14)&"") | E14: =IF($H14="","",IF(INDEX(Задачи!$E$1:$E$501,$H14)="","",INDEX(Задачи!$E$1:$E$501,$H14))) | F14: =IF($H14="","",IF(INDEX(Задачи!$F$1:$F$501,$H14)="","",INDEX(Задачи!$F$1:$F$501,$H14))) | G14: =IF($H14="","",INDEX(Задачи!$I$1:$I$501,$H14)&"") | H14: =IFERROR(MOD(LARGE(Задачи!$P$2:$P$501,ROWS(H$5:H14)),1000),"")
A15: =IF($H15="","",ROWS(A$5:A15)) | B15: =IF($H15="","",INDEX(Задачи!$A$1:$A$501,$H15)&"") | C15: =IF($H15="","",INDEX(Задачи!$B$1:$B$501,$H15)&"") | D15: =IF($H15="","",INDEX(Задачи!$C$1:$C$501,$H15)&"") | E15: =IF($H15="","",IF(INDEX(Задачи!$E$1:$E$501,$H15)="","",INDEX(Задачи!$E$1:$E$501,$H15))) | F15: =IF($H15="","",IF(INDEX(Задачи!$F$1:$F$501,$H15)="","",INDEX(Задачи!$F$1:$F$501,$H15))) | G15: =IF($H15="","",INDEX(Задачи!$I$1:$I$501,$H15)&"") | H15: =IFERROR(MOD(LARGE(Задачи!$P$2:$P$501,ROWS(H$5:H15)),1000),"")
A16: =IF($H16="","",ROWS(A$5:A16)) | B16: =IF($H16="","",INDEX(Задачи!$A$1:$A$501,$H16)&"") | C16: =IF($H16="","",INDEX(Задачи!$B$1:$B$501,$H16)&"") | D16: =IF($H16="","",INDEX(Задачи!$C$1:$C$501,$H16)&"") | E16: =IF($H16="","",IF(INDEX(Задачи!$E$1:$E$501,$H16)="","",INDEX(Задачи!$E$1:$E$501,$H16))) | F16: =IF($H16="","",IF(INDEX(Задачи!$F$1:$F$501,$H16)="","",INDEX(Задачи!$F$1:$F$501,$H16))) | G16: =IF($H16="","",INDEX(Задачи!$I$1:$I$501,$H16)&"") | H16: =IFERROR(MOD(LARGE(Задачи!$P$2:$P$501,ROWS(H$5:H16)),1000),"")
... A504: =IF($H504="","",ROWS(A$5:A504)) | B504: =IF($H504="","",INDEX(Задачи!$A$1:$A$501,$H504)&"") | C504: =IF($H504="","",INDEX(Задачи!$B$1:$B$501,$H504)&"") | D504: =IF($H504="","",INDEX(Задачи!$C$1:$C$501,$H504)&"") | E504: =IF($H504="","",IF(INDEX(Задачи!$E$1:$E$501,$H504)="","",INDEX(Задачи!$E$1:$E$501,$H504))) | F504: =IF($H504="","",IF(INDEX(Задачи!$F$1:$F$501,$H504)="","",INDEX(Задачи!$F$1:$F$501,$H504))) | G504: =IF($H504="","",INDEX(Задачи!$I$1:$I$501,$H504)&"") | H504: =IFERROR(MOD(LARGE(Задачи!$P$2:$P$501,ROWS(H$5:H504)),1000),"")

Sheet Справочники
A1: Категории (можно дописать ниже) | B1: Приоритеты | C1: Статусы | D1: Повтор | E1: Время | G1: Настройка | H1: Значение | J1: Фильтр: категория | K1: Фильтр: приоритет
A2: Промбаза | B2: Срочно | C2: Не начато | D2: Разово | E2: 15 мин | G2: Плановые = срок позже, чем через (дней) | H2: 7 | J2: Все | K2: Все
A3: Промбаза / маркетинг | B3: Высокий | C3: В работе | D3: Ежедневно | E3: 20–30 мин | J3: =IF(A2="","",A2) -> Промбаза | K3: =B2 -> Срочно
A4: Найм | B4: Средний | C4: Ожидает | D4: Еженедельно | E4: 30 мин | J4: =IF(A3="","",A3) -> Промбаза / маркетинг | K4: =B3 -> Высокий
A5: Подгузники / маркетинг | B5: Низкий | C5: Отложено | D5: Ежемесячно | E5: 30–45 мин | J5: =IF(A4="","",A4) -> Найм | K5: =B4 -> Средний
A6: Управление | C6: Выполнено | E6: 45 мин | J6: =IF(A5="","",A5) -> Подгузники / маркетинг | K6: =B5 -> Низкий
A7: Продажи / управление | E7: 1 час | J7: =IF(A6="","",A6) -> Управление
A8: Недвижимость | E8: 1–2 часа | J8: =IF(A7="","",A7) -> Продажи / управление
A9: Оптовка | E9: 2–3 часа | J9: =IF(A8="","",A8) -> Недвижимость
E10: Полдня | J10: =IF(A9="","",A9) -> Оптовка
E11: Весь день | J11: =IF(A10="","",A10)
J12: =IF(A11="","",A11)
J13: =IF(A12="","",A12)
J14: =IF(A13="","",A13)
J15: =IF(A14="","",A14)
J16: =IF(A15="","",A15)
J17: =IF(A16="","",A16)
A19: Синий текст и жёлтая ячейка — то, что можно менять. J:K служебные (для фильтров на «Главной»).

Sheet Инструкция
B1: КАК РАБОТАТЬ С ТАБЛИЦЕЙ
B3: Каждый день
B4: 1. Откройте «Главная»: сверху сводка, ниже — срочные и просроченные, текущие и плановые задачи.
B5: 2. Чтобы добавить или изменить задачу, перейдите на лист «Задачи» и заполните следующую пустую строку. Столбцы «Блок» и «Срок: осталось» не трогайте — они считаются сами.
B6: 3. Когда задача сделана, выберите в столбце «Статус» значение «Выполнено». Она сама уйдёт с «Главной» на лист «Выполненные» (на листе «Задачи» останется серой строкой — это общая база).
B8: Правила
B9: • Просрочено: срок раньше сегодняшней даты и статус не «Выполнено» — строка подсвечивается красным на «Задачи», срок и «Осталось» краснеют на «Главной».
B10: • Срочные: приоритет «Срочно», срок сегодня или просрочен. Плановые: статус «Отложено», приоритет «Низкий» или срок далее N дней (N — на листе «Справочники», по умолчанию 7).
B11: • Повторяющиеся задачи (Ежедневно / Еженедельно) без срока попадают в «Текущие» и показываются с пометкой ↻.
B12: • Задача без приоритета и без срока попадает в «Текущие» — присвойте ей приоритет, чтобы навести порядок.
B14: Фильтры
B15: • «Главная»: выберите категорию и/или приоритет в жёлтых ячейках (значение «Все» — без фильтра).
... B26: • Категории в строках, где они были пусты, проставлены по смыслу (Оптовка, Управление, Найм) — проверьте и поправьте при необходимости.
